{
  "domain": "Agriculture & Forestry",
  "count": 6,
  "items": [
    {
      "title": "ΠΡΟΜΗΘΕΙΑ ΥΛΙΚΩΝ ΚΑΙ ΤΟΠΟΘΕΤΗΣΗ ΞΥΛΙΝΟΥ ΔΑΠΕΔΟΥ ΣΤΗ ΣΚΗΝΗ ΤΟΥ ΚΩΘ & ΑΛΛΩΝ ΣΥΝΑΦΩΝ ΤΕΧΝΙΚΩΝ ΕΡΓΑΣΙΩΝ",
      "referenceNumber": "26PROC018474600",
      "signedDate": "2026-02-12T00:00:00",
      "publishedDate": null,
      "finalSubmissionDate": "2026-02-17T14:00:00",
      "submissionDate": "2026-02-12T18:25:44.795",
      "lastUpdateDate": null,
      "cancelled": false,
      "cancellationDate": null,
      "cancellationType": null,
      "cancellationReason": null,
      "cancellationADA": null,
      "amendPreviousNotice": false,
      "amendedNoticeADAM": null,
      "frameworkAgreementNoticeADAM": null,
      "protocolNumber": null,
      "authorEmail": null,
      "aaht": "1022.E00372.0001",
      "biddingWebsite": null,
      "organizationVatNumber": null,
      "greekOrganizationVatNumber": null,
      "budget": null,
      "commitmentNo": null,
      "relatedNoticeADAM": null,
      "numberOfSections": 2,
      "nutsCode": {
        "key": "EL522",
        "value": "Θεσσαλονίκη"
      },
      "nutsCity": "ΘΕΣΣΑΛΟΝΙΚΗ",
      "nutsPostalCode": "54625",
      "nutsCountry": {
        "key": "GR",
        "value": "Ελλάδα"
      },
      "assignedContract": {
        "key": "1",
        "value": "Ναι"
      },
      "socialContract": {
        "key": "2",
        "value": "Όχι"
      },
      "centralGovernmentAuthority": {
        "key": "2",
        "value": "Όχι"
      },
      "contractingData": {
        "unitsOperator": {
          "key": "76276",
          "value": "ΚΡΑΤΙΚΟ ΩΔΕΙΟ ΘΕΣΣΑΛΟΝΙΚΗΣ"
        },
        "signers": {
          "key": "100070399",
          "value": "ΝΙΚΟΛΑΟΣ ΑΒΔΕΛΛΑΣ - Πρόεδρος Δ.Σ."
        }
      },
      "fundingDetails": {
        "publicFundingRef": null,
        "publicFundingRefNum": null,
        "publicFundingRefOps": null,
        "cofundProgramRef": null,
        "selfFundProgramRef": null,
        "espaFundProgramRef": null,
        "regularBudgetFundedProgramRef": "2410108, 2420389"
      },
      "systemicNumbers": [],
      "approvedRequests": [
        {
          "code": "26REQ018366761"
        },
        {
          "code": "26REQ018366760"
        }
      ],
      "contractingAuthorities": [
        {
          "contractingAuthority": {
            "key": "9",
            "value": "ΝΠΔΔ"
          }
        }
      ],
      "nutsCodes": [
        {
          "nutsCode": {
            "key": "EL522",
            "value": "Θεσσαλονίκη"
          }
        }
      ],
      "organization": {
        "key": "99221386",
        "value": "ΚΡΑΤΙΚΟ ΩΔΕΙΟ ΘΕΣΣΑΛΟΝΙΚΗΣ"
      },
      "typeOfProcedure": {
        "key": "6",
        "value": "Απευθείας ανάθεση"
      },
      "contractType": {
        "key": "9",
        "value": "Υπηρεσίες"
      },
      "awardProcedure": null,
      "centralizedMarkets": [
        {
          "centralizedMarket": {
            "key": "8",
            "value": "Δεν χρησιμοποιείται"
          }
        }
      ],
      "legalContext": {
        "key": "5",
        "value": "ν.4412/2016 - Βιβλίο Ι – κάτω των ορίων"
      },
      "conductingProceedings": {
        "key": "2",
        "value": "Μη ηλεκτρονική διαδικασία"
      },
      "digitalPlatform": null,
      "criteriaCode": {
        "key": "1",
        "value": "Βάσει κόστους – βέλτιστη σχέση ποιότητας – τιμής"
      },
      "classificationOfPublicLawOrganization": {
        "key": "1",
        "value": "Κεντρική Κυβέρνηση"
      },
      "noticeType": {
        "key": "4",
        "value": "Πρόσκληση"
      },
      "contractingAuthorityActivity": {
        "key": "10",
        "value": "Πολιτισμός και θρησκεία"
      },
      "contractDuration": 2,
      "contractDurationUnitOfMeasure": {
        "key": "3",
        "value": "Μήνες"
      },
      "totalCostWithVAT": 11160.0,
      "totalCostWithoutVAT": 9000.0,
      "objectDetails": [
        {
          "quantity": 1,
          "type": {
            "key": "E48",
            "value": "Υπηρεσία"
          },
          "costWithoutVAT": 6700,
          "vat": "24",
          "currency": {
            "key": "EUR",
            "value": "Ευρώ"
          },
          "shortDescription": "ΕΡΓΑΣΙΕΣ ΤΟΠΟΘΕΤΗΣΗΣ ΞΥΛΙΝΟΥ ΔΑΠΕΔΟΥ ΣΤΗ ΣΚΗΝΗ ΤΟΥ ΚΩΘ",
          "cpvs": [
            {
              "key": "45432114-6",
              "value": "Τοποθέτηση ξύλινων δαπέδων"
            }
          ],
          "greenContracts": {
            "key": "1",
            "value": "Δεν εμπίπτει στο ΕΣΔ"
          },
          "goodServices": null,
          "budgetCode": null
        },
        {
          "quantity": 1,
          "type": {
            "key": "C62",
            "value": "Τεμάχιο"
          },
          "costWithoutVAT": 2300,
          "vat": "24",
          "currency": {
            "key": "EUR",
            "value": "Ευρώ"
          },
          "shortDescription": "ΠΡΟΜΗΘΕΙΑ ΥΛΙΚΩΝ ΓΙΑ ΤΗΝ ΤΟΠΟΘΕΤΗΣΗ ΞΥΛΙΝΟΥ ΔΑΠΕΔΟΥ ΣΤΗ ΣΚΗΝΗ ΤΟΥ ΚΩΘ",
          "cpvs": [
            {
              "key": "03419100-1",
              "value": "Προϊόντα ξυλείας"
            }
          ],
          "greenContracts": {
            "key": "1",
            "value": "Δεν εμπίπτει στο ΕΣΔ"
          },
          "goodServices": null,
          "budgetCode": null
        }
      ],
      "additionalContractTypes": [
        {
          "additionalContractType": {
            "key": "2",
            "value": "Προμήθειες"
          }
        }
      ],
      "mixedContract": true,
      "offersValidTime": 1,
      "offersValidTimeUnitOfMeasure": {
        "key": "3",
        "value": "Μήνες"
      },
      "maxNumberOfContractors": null,
      "optionRight": {
        "key": "2",
        "value": "Όχι"
      },
      "optionRightDescription": null,
      "abortReason": null,
      "auctionRefNo": [],
      "amendsNoticeRefNo": [],
      "cpv_codes_extracted": [
        "99221386",
        "45432114",
        "03419100"
      ],
      "cpv_divisions": [
        "45",
        "03"
      ],
      "all_domains": [
        "Construction & Works",
        "Agriculture & Forestry"
      ],
      "primary_domain": "Construction & Works"
    },
    {
      "title": "ΠΡΟΣΚΛΗΣΗ 472 ΥΠΟΒΟΛΗΣ ΠΡΟΣΦΟΡΑΣ ΓΙΑ  ΠΡΟΜΗΘΕΙΑ ΣΚΗΝΟΓΡΑΦΙΚΟΥ ΥΛΙΚΟΥ – ΞΥΛΕΙΑ (ΗΛΙΟΣ ΜΕ ΞΙΦΟΛΟΓΧΕΣ)",
      "referenceNumber": "26PROC018474477",
      "signedDate": "2026-02-12T00:00:00",
      "publishedDate": null,
      "finalSubmissionDate": "2026-02-18T10:00:00",
      "submissionDate": "2026-02-12T15:55:52.879",
      "lastUpdateDate": null,
      "cancelled": false,
      "cancellationDate": null,
      "cancellationType": null,
      "cancellationReason": null,
      "cancellationADA": null,
      "amendPreviousNotice": false,
      "amendedNoticeADAM": null,
      "frameworkAgreementNoticeADAM": null,
      "protocolNumber": null,
      "authorEmail": null,
      "aaht": "1022.E00369.0001",
      "biddingWebsite": null,
      "organizationVatNumber": null,
      "greekOrganizationVatNumber": null,
      "budget": null,
      "commitmentNo": null,
      "relatedNoticeADAM": null,
      "numberOfSections": 1,
      "nutsCode": {
        "key": "EL",
        "value": "ΕΛΛΑΔΑ"
      },
      "nutsCity": "ΘΕΣΣΑΛΟΝΙΚΗ",
      "nutsPostalCode": "54621",
      "nutsCountry": {
        "key": "GR",
        "value": "Ελλάδα"
      },
      "assignedContract": {
        "key": "1",
        "value": "Ναι"
      },
      "socialContract": {
        "key": "2",
        "value": "Όχι"
      },
      "centralGovernmentAuthority": {
        "key": "2",
        "value": "Όχι"
      },
      "contractingData": {
        "unitsOperator": {
          "key": "77792",
          "value": "ΚΑΛΛΙΤΕΧΝΙΚΗ ΔΙΕΥΘΥΝΣΗ"
        },
        "signers": {
          "key": "100072411",
          "value": "ΑΣΤΕΡΙΟΣ ΠΕΛΤΕΚΗΣ - Διευθυντής"
        }
      },
      "fundingDetails": {
        "publicFundingRef": null,
        "publicFundingRefNum": null,
        "publicFundingRefOps": null,
        "cofundProgramRef": null,
        "selfFundProgramRef": null,
        "espaFundProgramRef": null,
        "regularBudgetFundedProgramRef": "74.03/25"
      },
      "systemicNumbers": [],
      "approvedRequests": [
        {
          "code": "26REQ018474469"
        }
      ],
      "contractingAuthorities": [
        {
          "contractingAuthority": {
            "key": "10",
            "value": "ΝΠΙΔ"
          }
        }
      ],
      "nutsCodes": [
        {
          "nutsCode": {
            "key": "EL",
            "value": "ΕΛΛΑΔΑ"
          }
        }
      ],
      "organization": {
        "key": "99221384",
        "value": "ΚΡΑΤΙΚΟ ΘΕΑΤΡΟ ΒΟΡΕΙΟΥ ΕΛΛΑΔΟΣ"
      },
      "typeOfProcedure": {
        "key": "6",
        "value": "Απευθείας ανάθεση"
      },
      "contractType": {
        "key": "13",
        "value": "Προμήθειες"
      },
      "awardProcedure": null,
      "centralizedMarkets": [
        {
          "centralizedMarket": {
            "key": "8",
            "value": "Δεν χρησιμοποιείται"
          }
        }
      ],
      "legalContext": {
        "key": "5",
        "value": "ν.4412/2016 - Βιβλίο Ι – κάτω των ορίων"
      },
      "conductingProceedings": {
        "key": "2",
        "value": "Μη ηλεκτρονική διαδικασία"
      },
      "digitalPlatform": null,
      "criteriaCode": {
        "key": "1",
        "value": "Βάσει κόστους – βέλτιστη σχέση ποιότητας – τιμής"
      },
      "classificationOfPublicLawOrganization": {
        "key": "4",
        "value": "Εκτός Γενικής Κυβέρνησης"
      },
      "noticeType": {
        "key": "4",
        "value": "Πρόσκληση"
      },
      "contractingAuthorityActivity": {
        "key": "10",
        "value": "Πολιτισμός και θρησκεία"
      },
      "contractDuration": 3,
      "contractDurationUnitOfMeasure": {
        "key": "3",
        "value": "Μήνες"
      },
      "totalCostWithVAT": 4629.19,
      "totalCostWithoutVAT": 3733.22,
      "objectDetails": [
        {
          "quantity": 132,
          "type": {
            "key": "C62",
            "value": "Τεμάχιο"
          },
          "costWithoutVAT": 3733.22,
          "vat": "24",
          "currency": {
            "key": "EUR",
            "value": "Ευρώ"
          },
          "shortDescription": "ΞΥΛΕΙΑ   17 ΜΑΔΕΡΙΑ 510CM*15CM*5CM   35 ΦΥΛΛΑ ΠΛΑΚΑΖ 250CM* 122CM* 1.8CM   20 ΦΥΛΛΑ ΚΟΝΤΡΑΠΛΑΚΕ 250CM* 122CM* 0.9 MM   20 ΦΥΛΛΑ ΚΟΝΤΡΑΠΛΑΚΕ 250CM* 122CM* 0.6 MM   40 ΣΑΝΙΔΕΣ ASORT 350CM* 14CM * 2CM* ΣΟΥΗΔΙΚΗ",
          "cpvs": [
            {
              "key": "03419000-0",
              "value": "Ξυλεία"
            }
          ],
          "greenContracts": {
            "key": "1",
            "value": "Δεν εμπίπτει στο ΕΣΔ"
          },
          "goodServices": null,
          "budgetCode": null
        }
      ],
      "additionalContractTypes": null,
      "mixedContract": false,
      "offersValidTime": 3,
      "offersValidTimeUnitOfMeasure": {
        "key": "3",
        "value": "Μήνες"
      },
      "maxNumberOfContractors": null,
      "optionRight": {
        "key": "2",
        "value": "Όχι"
      },
      "optionRightDescription": null,
      "abortReason": null,
      "auctionRefNo": [],
      "amendsNoticeRefNo": [],
      "cpv_codes_extracted": [
        "99221384",
        "03419000"
      ],
      "cpv_divisions": [
        "03"
      ],
      "all_domains": [
        "Agriculture & Forestry"
      ],
      "primary_domain": "Agriculture & Forestry"
    },
    {
      "title": "Πρόσκληση για αποστολή οικονομικής προσφοράς",
      "referenceNumber": "26PROC018474192",
      "signedDate": "2026-02-12T00:00:00",
      "publishedDate": null,
      "finalSubmissionDate": "2026-02-19T14:00:00",
      "submissionDate": "2026-02-12T14:30:52.584",
      "lastUpdateDate": null,
      "cancelled": false,
      "cancellationDate": null,
      "cancellationType": null,
      "cancellationReason": null,
      "cancellationADA": null,
      "amendPreviousNotice": false,
      "amendedNoticeADAM": null,
      "frameworkAgreementNoticeADAM": null,
      "protocolNumber": null,
      "authorEmail": null,
      "aaht": "1007.Ε82207.0001",
      "biddingWebsite": null,
      "organizationVatNumber": null,
      "greekOrganizationVatNumber": null,
      "budget": null,
      "commitmentNo": null,
      "relatedNoticeADAM": null,
      "numberOfSections": 2,
      "nutsCode": {
        "key": "EL612",
        "value": "Λάρισα"
      },
      "nutsCity": "Φάρσαλα",
      "nutsPostalCode": "40300",
      "nutsCountry": {
        "key": "GR",
        "value": "Ελλάδα"
      },
      "assignedContract": {
        "key": "1",
        "value": "Ναι"
      },
      "socialContract": {
        "key": "2",
        "value": "Όχι"
      },
      "centralGovernmentAuthority": {
        "key": "2",
        "value": "Όχι"
      },
      "contractingData": {
        "unitsOperator": {
          "key": "82057",
          "value": "ΤΜΗΜΑ  ΠΡΟΥΠΟΛΟΓΙΣΜΟΥ ΛΟΓΙΣΤΗΡΙΟΥ ΚΑΙ ΠΡΟΜΗΘΕΙΩΝ"
        },
        "signers": {
          "key": "100048969",
          "value": "Ιορδάνης (Μάκης) Εσκιόγλου - Δήμαρχος"
        }
      },
      "fundingDetails": {
        "publicFundingRef": null,
        "publicFundingRefNum": null,
        "publicFundingRefOps": null,
        "cofundProgramRef": null,
        "selfFundProgramRef": null,
        "espaFundProgramRef": null,
        "regularBudgetFundedProgramRef": "0611"
      },
      "systemicNumbers": [],
      "approvedRequests": [],
      "contractingAuthorities": [
        {
          "contractingAuthority": {
            "key": "9",
            "value": "ΝΠΔΔ"
          }
        }
      ],
      "nutsCodes": [
        {
          "nutsCode": {
            "key": "EL612",
            "value": "Λάρισα"
          }
        }
      ],
      "organization": {
        "key": "6306",
        "value": "ΔΗΜΟΣ ΦΑΡΣΑΛΩΝ"
      },
      "typeOfProcedure": {
        "key": "6",
        "value": "Απευθείας ανάθεση"
      },
      "contractType": {
        "key": "13",
        "value": "Προμήθειες"
      },
      "awardProcedure": null,
      "centralizedMarkets": [
        {
          "centralizedMarket": {
            "key": "8",
            "value": "Δεν χρησιμοποιείται"
          }
        }
      ],
      "legalContext": {
        "key": "4",
        "value": "ν.4412/2016 - Βιβλίο Ι – άνω των ορίων"
      },
      "conductingProceedings": {
        "key": "2",
        "value": "Μη ηλεκτρονική διαδικασία"
      },
      "digitalPlatform": null,
      "criteriaCode": {
        "key": "4",
        "value": "Βάσει κόστους – άλλο"
      },
      "classificationOfPublicLawOrganization": {
        "key": "2",
        "value": "ΟΤΑ"
      },
      "noticeType": {
        "key": "4",
        "value": "Πρόσκληση"
      },
      "contractingAuthorityActivity": {
        "key": "1",
        "value": "Γενικές δημόσιες υπηρεσίες"
      },
      "contractDuration": 1,
      "contractDurationUnitOfMeasure": {
        "key": "2",
        "value": "Εβδομάδες"
      },
      "totalCostWithVAT": 2209.15,
      "totalCostWithoutVAT": 1955.0,
      "objectDetails": [
        {
          "quantity": 1285,
          "type": {
            "key": "KGM",
            "value": "Kg"
          },
          "costWithoutVAT": 1955,
          "vat": "13",
          "currency": {
            "key": "EUR",
            "value": "Ευρώ"
          },
          "shortDescription": "ΟΜΑΔΑ Ε5  ΑΝΤΙΚΕΙΜΕΝΟ:  ΠΡΟΜΗΘΕΙΑ ΕΙΔΩΝ ΟΠΩΡΟΠΩΛΕΙΟΥ Α’ & Β’ ΠΑΙΔΙΚΟΥ ΣΤΑΘΜΟΥ  ΟΜΑΔΑ  Ε10 ΑΝΤΙΚΕΙΜΕΝΟ: ΕΙΔΩΝ ΟΠΩΡΟΠΩΛΕΙΟΥ ΓΙΑ  ΤΟΝ ΠΑΙΔΙΚΟ ΣΤΑΘΜΟ «ΤΟ ΠΑΡΚΟ ΤΗΣ  ΧΑΡΑΣ»  ",
          "cpvs": [
            {
              "key": "03220000-9",
              "value": "Λαχανικά"
            }
          ],
          "greenContracts": {
            "key": "1",
            "value": "Δεν εμπίπτει στο ΕΣΔ"
          },
          "goodServices": null,
          "budgetCode": null
        }
      ],
      "additionalContractTypes": null,
      "mixedContract": false,
      "offersValidTime": 1,
      "offersValidTimeUnitOfMeasure": {
        "key": "2",
        "value": "Εβδομάδες"
      },
      "maxNumberOfContractors": null,
      "optionRight": {
        "key": "2",
        "value": "Όχι"
      },
      "optionRightDescription": null,
      "abortReason": null,
      "auctionRefNo": [],
      "amendsNoticeRefNo": [],
      "cpv_codes_extracted": [
        "03220000"
      ],
      "cpv_divisions": [
        "03"
      ],
      "all_domains": [
        "Agriculture & Forestry"
      ],
      "primary_domain": "Agriculture & Forestry"
    },
    {
      "title": "Πρόσκληση υποβολής προσφοράς",
      "referenceNumber": "26PROC018472271",
      "signedDate": "2026-02-12T00:00:00",
      "publishedDate": null,
      "finalSubmissionDate": "2026-02-17T16:00:00",
      "submissionDate": "2026-02-12T12:10:01.395",
      "lastUpdateDate": null,
      "cancelled": false,
      "cancellationDate": null,
      "cancellationType": null,
      "cancellationReason": null,
      "cancellationADA": null,
      "amendPreviousNotice": false,
      "amendedNoticeADAM": null,
      "frameworkAgreementNoticeADAM": null,
      "protocolNumber": null,
      "authorEmail": null,
      "aaht": "1007.E87415.0001",
      "biddingWebsite": null,
      "organizationVatNumber": null,
      "greekOrganizationVatNumber": null,
      "budget": null,
      "commitmentNo": null,
      "relatedNoticeADAM": null,
      "numberOfSections": 2,
      "nutsCode": {
        "key": "EL531",
        "value": "Γρεβενά, Κοζάνη"
      },
      "nutsCity": "ΒΕΛΒΕΝΤΟ",
      "nutsPostalCode": "50400",
      "nutsCountry": {
        "key": "GR",
        "value": "Ελλάδα"
      },
      "assignedContract": {
        "key": "2",
        "value": "Όχι"
      },
      "socialContract": {
        "key": "2",
        "value": "Όχι"
      },
      "centralGovernmentAuthority": {
        "key": "2",
        "value": "Όχι"
      },
      "contractingData": {
        "unitsOperator": {
          "key": "100054436",
          "value": "ΔΙΕΥΘΥΝΣΗ ΔΙΟΙΚΗΤΙΚΩΝ ΚΑΙ ΟΙΚΟΝΟΜΙΚΩΝ ΥΠΗΡΕΣΙΩΝ"
        },
        "signers": {
          "key": "100049820",
          "value": "ΜΑΝΩΛΗΣ ΣΤΕΡΓΙΟΥ - Δήμαρχος"
        }
      },
      "fundingDetails": {
        "publicFundingRef": null,
        "publicFundingRefNum": null,
        "publicFundingRefOps": null,
        "cofundProgramRef": null,
        "selfFundProgramRef": null,
        "espaFundProgramRef": null,
        "regularBudgetFundedProgramRef": "070.2420908004"
      },
      "systemicNumbers": [],
      "approvedRequests": [
        {
          "code": "26REQ018471004"
        }
      ],
      "contractingAuthorities": [
        {
          "contractingAuthority": {
            "key": "9",
            "value": "ΝΠΔΔ"
          }
        }
      ],
      "nutsCodes": [
        {
          "nutsCode": {
            "key": "EL531",
            "value": "Γρεβενά, Κοζάνη"
          }
        }
      ],
      "organization": {
        "key": "100048875",
        "value": "ΔΗΜΟΣ ΒΕΛΒΕΝΤΟΥ"
      },
      "typeOfProcedure": {
        "key": "6",
        "value": "Απευθείας ανάθεση"
      },
      "contractType": {
        "key": "13",
        "value": "Προμήθειες"
      },
      "awardProcedure": null,
      "centralizedMarkets": [
        {
          "centralizedMarket": {
            "key": "8",
            "value": "Δεν χρησιμοποιείται"
          }
        }
      ],
      "legalContext": {
        "key": "5",
        "value": "ν.4412/2016 - Βιβλίο Ι – κάτω των ορίων"
      },
      "conductingProceedings": {
        "key": "2",
        "value": "Μη ηλεκτρονική διαδικασία"
      },
      "digitalPlatform": null,
      "criteriaCode": {
        "key": "4",
        "value": "Βάσει κόστους – άλλο"
      },
      "classificationOfPublicLawOrganization": {
        "key": "2",
        "value": "ΟΤΑ"
      },
      "noticeType": {
        "key": "4",
        "value": "Πρόσκληση"
      },
      "contractingAuthorityActivity": {
        "key": "1",
        "value": "Γενικές δημόσιες υπηρεσίες"
      },
      "contractDuration": 4,
      "contractDurationUnitOfMeasure": {
        "key": "3",
        "value": "Μήνες"
      },
      "totalCostWithVAT": 430.57,
      "totalCostWithoutVAT": 364.0,
      "objectDetails": [
        {
          "quantity": 1,
          "type": {
            "key": "C62",
            "value": "Τεμάχιο"
          },
          "costWithoutVAT": 189,
          "vat": "13",
          "currency": {
            "key": "EUR",
            "value": "Ευρώ"
          },
          "shortDescription": "Εκδήλωση της Θρησκευτικής Εορτής των Τριών Ιεραρχών σύμφωνα με την 11/2026",
          "cpvs": [
            {
              "key": "15810000-9",
              "value": "Αρτοσκευάσματα"
            }
          ],
          "greenContracts": {
            "key": "1",
            "value": "Δεν εμπίπτει στο ΕΣΔ"
          },
          "goodServices": null,
          "budgetCode": null
        },
        {
          "quantity": 1,
          "type": {
            "key": "C62",
            "value": "Τεμάχιο"
          },
          "costWithoutVAT": 175,
          "vat": "24",
          "currency": {
            "key": "EUR",
            "value": "Ευρώ"
          },
          "shortDescription": "Εκδήλωση της Θρησκευτικής Εορτής των Τριών Ιεραρχών σύμφωνα με την 11/2026",
          "cpvs": [
            {
              "key": "03121210-0",
              "value": "Άνθινες διατάξεις"
            }
          ],
          "greenContracts": {
            "key": "1",
            "value": "Δεν εμπίπτει στο ΕΣΔ"
          },
          "goodServices": null,
          "budgetCode": null
        }
      ],
      "additionalContractTypes": null,
      "mixedContract": false,
      "offersValidTime": 1,
      "offersValidTimeUnitOfMeasure": {
        "key": "3",
        "value": "Μήνες"
      },
      "maxNumberOfContractors": null,
      "optionRight": {
        "key": "2",
        "value": "Όχι"
      },
      "optionRightDescription": null,
      "abortReason": null,
      "auctionRefNo": [],
      "amendsNoticeRefNo": [],
      "cpv_codes_extracted": [
        "15810000",
        "03121210"
      ],
      "cpv_divisions": [
        "15",
        "03"
      ],
      "all_domains": [
        "Food & Catering",
        "Agriculture & Forestry"
      ],
      "primary_domain": "Food & Catering"
    },
    {
      "title": " ΝΩΠΑ ΟΠΩΡΟΛΑΧΑΝΙΚΑ (ΑΡ ΠΡΩΤΟΚ 2422 _ ΕΝΤΟΛΗ 585_ΔΙΑΓ 3014)",
      "referenceNumber": "26PROC018469996",
      "signedDate": "2026-02-11T00:00:00",
      "publishedDate": null,
      "finalSubmissionDate": "2026-02-18T12:00:00",
      "submissionDate": "2026-02-12T10:14:36.423",
      "lastUpdateDate": null,
      "cancelled": false,
      "cancellationDate": null,
      "cancellationType": null,
      "cancellationReason": null,
      "cancellationADA": null,
      "amendPreviousNotice": false,
      "amendedNoticeADAM": null,
      "frameworkAgreementNoticeADAM": null,
      "protocolNumber": null,
      "authorEmail": null,
      "aaht": "1015.E00172.0001",
      "biddingWebsite": "http://www.tzaneio.gov.gr/promithies/mikropromithies/",
      "organizationVatNumber": null,
      "greekOrganizationVatNumber": null,
      "budget": null,
      "commitmentNo": null,
      "relatedNoticeADAM": null,
      "numberOfSections": 2,
      "nutsCode": {
        "key": "EL307",
        "value": "Πειραιάς, Νήσοι"
      },
      "nutsCity": "ΠΕΙΡΑΙΑΣ ΑΤΤΙΚΗΣ",
      "nutsPostalCode": "18536",
      "nutsCountry": {
        "key": "GR",
        "value": "Ελλάδα"
      },
      "assignedContract": {
        "key": "2",
        "value": "Όχι"
      },
      "socialContract": {
        "key": "2",
        "value": "Όχι"
      },
      "centralGovernmentAuthority": {
        "key": "2",
        "value": "Όχι"
      },
      "contractingData": {
        "unitsOperator": {
          "key": "95452",
          "value": "ΔΙΑΧΕΙΡΙΣΗ ΤΡΟΦΙΜΩΝ"
        },
        "signers": {
          "key": "100096910",
          "value": "ΑΝΑΣΤΑΣΙΟΣ ΜΥΤΟΓΛΟΥ - Διοικητής"
        }
      },
      "fundingDetails": {
        "publicFundingRef": null,
        "publicFundingRefNum": null,
        "publicFundingRefOps": null,
        "cofundProgramRef": null,
        "selfFundProgramRef": null,
        "espaFundProgramRef": null,
        "regularBudgetFundedProgramRef": "32309020000001"
      },
      "systemicNumbers": [
        {
          "systemicNumber": "585/2026 ΔΙΑΓ 3014"
        }
      ],
      "approvedRequests": [
        {
          "code": "26REQ018469515"
        }
      ],
      "contractingAuthorities": [
        {
          "contractingAuthority": {
            "key": "9",
            "value": "ΝΠΔΔ"
          }
        }
      ],
      "nutsCodes": [
        {
          "nutsCode": {
            "key": "EL307",
            "value": "Πειραιάς, Νήσοι"
          }
        }
      ],
      "organization": {
        "key": "99222008",
        "value": "ΠΕΡ.ΓΕΝ. ΝΟΣΟΚΟΜΕΙΟ ΠΕΙΡΑΙΩΣ 'ΤΖΑΝΕΙΟ'"
      },
      "typeOfProcedure": {
        "key": "6",
        "value": "Απευθείας ανάθεση"
      },
      "contractType": {
        "key": "13",
        "value": "Προμήθειες"
      },
      "awardProcedure": null,
      "centralizedMarkets": [
        {
          "centralizedMarket": {
            "key": "8",
            "value": "Δεν χρησιμοποιείται"
          }
        }
      ],
      "legalContext": {
        "key": "5",
        "value": "ν.4412/2016 - Βιβλίο Ι – κάτω των ορίων"
      },
      "conductingProceedings": {
        "key": "1",
        "value": "Ηλεκτρονική Διαδικασία"
      },
      "digitalPlatform": {
        "key": "7",
        "value": "Άλλη"
      },
      "criteriaCode": {
        "key": "2",
        "value": "Βάσει τιμής"
      },
      "classificationOfPublicLawOrganization": {
        "key": "4",
        "value": "Εκτός Γενικής Κυβέρνησης"
      },
      "noticeType": {
        "key": "4",
        "value": "Πρόσκληση"
      },
      "contractingAuthorityActivity": {
        "key": "6",
        "value": "Υγεία"
      },
      "contractDuration": 3,
      "contractDurationUnitOfMeasure": {
        "key": "3",
        "value": "Μήνες"
      },
      "totalCostWithVAT": 9102.15,
      "totalCostWithoutVAT": 8055.0,
      "objectDetails": [
        {
          "quantity": 4500,
          "type": {
            "key": "KGM",
            "value": "Kg"
          },
          "costWithoutVAT": 8055,
          "vat": "13",
          "currency": {
            "key": "EUR",
            "value": "Ευρώ"
          },
          "shortDescription": "ΜΗΛΑ- ΠΟΡΤΟΚΑΛΙΑ",
          "cpvs": [
            {
              "key": "03222000-3",
              "value": "Φρούτα και καρποί"
            }
          ],
          "greenContracts": {
            "key": "1",
            "value": "Δεν εμπίπτει στο ΕΣΔ"
          },
          "goodServices": null,
          "budgetCode": null
        }
      ],
      "additionalContractTypes": null,
      "mixedContract": false,
      "offersValidTime": 90,
      "offersValidTimeUnitOfMeasure": {
        "key": "1",
        "value": "Ημέρες"
      },
      "maxNumberOfContractors": null,
      "optionRight": {
        "key": "2",
        "value": "Όχι"
      },
      "optionRightDescription": null,
      "abortReason": null,
      "auctionRefNo": [],
      "amendsNoticeRefNo": [],
      "cpv_codes_extracted": [
        "99222008",
        "03222000"
      ],
      "cpv_divisions": [
        "03"
      ],
      "all_domains": [
        "Agriculture & Forestry"
      ],
      "primary_domain": "Agriculture & Forestry"
    },
    {
      "title": "ΠΡΟΣΚΛΗΣΗ ΓΙΑ ΤΗΝ ΠΡΟΜΗΘΕΙΑ ΣΥΣΚΕΥΑΣΜΕΝΩΝ ΣΑΛΑΤΩΝ",
      "referenceNumber": "26PROC018468679",
      "signedDate": "2026-02-11T00:00:00",
      "publishedDate": null,
      "finalSubmissionDate": "2026-02-16T13:00:00",
      "submissionDate": "2026-02-12T09:00:37.389",
      "lastUpdateDate": null,
      "cancelled": false,
      "cancellationDate": null,
      "cancellationType": null,
      "cancellationReason": null,
      "cancellationADA": null,
      "amendPreviousNotice": false,
      "amendedNoticeADAM": null,
      "frameworkAgreementNoticeADAM": null,
      "protocolNumber": null,
      "authorEmail": null,
      "aaht": "1011.2020000000.0029",
      "biddingWebsite": null,
      "organizationVatNumber": null,
      "greekOrganizationVatNumber": null,
      "budget": null,
      "commitmentNo": null,
      "relatedNoticeADAM": null,
      "numberOfSections": 1,
      "nutsCode": {
        "key": "EL613",
        "value": "Μαγνησία, Σποράδες"
      },
      "nutsCity": "ΒΟΛΟΣ",
      "nutsPostalCode": "38446",
      "nutsCountry": {
        "key": "GR",
        "value": "Ελλάδα"
      },
      "assignedContract": {
        "key": "2",
        "value": "Όχι"
      },
      "socialContract": {
        "key": "2",
        "value": "Όχι"
      },
      "centralGovernmentAuthority": {
        "key": "2",
        "value": "Όχι"
      },
      "contractingData": {
        "unitsOperator": {
          "key": "87929",
          "value": "ΓΕΣ/32 ΤΑΞ Π/Ν"
        },
        "signers": {
          "key": "100102006",
          "value": "ΝΙΚΟΛΑΟΣ ΚΟΥΤΕΛΗΣ - Διοικητής"
        }
      },
      "fundingDetails": {
        "publicFundingRef": null,
        "publicFundingRefNum": null,
        "publicFundingRefOps": null,
        "cofundProgramRef": null,
        "selfFundProgramRef": "-",
        "espaFundProgramRef": null,
        "regularBudgetFundedProgramRef": null
      },
      "systemicNumbers": [],
      "approvedRequests": [
        {
          "code": "26REQ018417301"
        }
      ],
      "contractingAuthorities": [
        {
          "contractingAuthority": {
            "key": "9",
            "value": "ΝΠΔΔ"
          }
        }
      ],
      "nutsCodes": [
        {
          "nutsCode": {
            "key": "EL613",
            "value": "Μαγνησία, Σποράδες"
          }
        }
      ],
      "organization": {
        "key": "6",
        "value": "ΥΠΟΥΡΓΕΙΟ ΕΘΝΙΚΗΣ ΑΜΥΝΑΣ"
      },
      "typeOfProcedure": {
        "key": "6",
        "value": "Απευθείας ανάθεση"
      },
      "contractType": {
        "key": "13",
        "value": "Προμήθειες"
      },
      "awardProcedure": null,
      "centralizedMarkets": [
        {
          "centralizedMarket": {
            "key": "8",
            "value": "Δεν χρησιμοποιείται"
          }
        }
      ],
      "legalContext": {
        "key": "7",
        "value": "ν.4412/2016 - Βιβλίο ΙΙ – κάτω των ορίων"
      },
      "conductingProceedings": {
        "key": "2",
        "value": "Μη ηλεκτρονική διαδικασία"
      },
      "digitalPlatform": null,
      "criteriaCode": {
        "key": "2",
        "value": "Βάσει τιμής"
      },
      "classificationOfPublicLawOrganization": {
        "key": "4",
        "value": "Εκτός Γενικής Κυβέρνησης"
      },
      "noticeType": {
        "key": "4",
        "value": "Πρόσκληση"
      },
      "contractingAuthorityActivity": {
        "key": "2",
        "value": "Άμυνα"
      },
      "contractDuration": 1,
      "contractDurationUnitOfMeasure": {
        "key": "4",
        "value": "Έτη"
      },
      "totalCostWithVAT": 14113.7,
      "totalCostWithoutVAT": 12490.0,
      "objectDetails": [
        {
          "quantity": 4,
          "type": {
            "key": "C62",
            "value": "Τεμάχιο"
          },
          "costWithoutVAT": 12490,
          "vat": "13",
          "currency": {
            "key": "EUR",
            "value": "Ευρώ"
          },
          "shortDescription": "Πρόσκληση υποβολής προσφορών για την προμήθεια συσκευασμένων σαλατών.",
          "cpvs": [
            {
              "key": "03221320-5",
              "value": "Πράσινες σαλάτες"
            }
          ],
          "greenContracts": {
            "key": "1",
            "value": "Δεν εμπίπτει στο ΕΣΔ"
          },
          "goodServices": null,
          "budgetCode": null
        }
      ],
      "additionalContractTypes": null,
      "mixedContract": false,
      "offersValidTime": 4,
      "offersValidTimeUnitOfMeasure": {
        "key": "3",
        "value": "Μήνες"
      },
      "maxNumberOfContractors": null,
      "optionRight": {
        "key": "2",
        "value": "Όχι"
      },
      "optionRightDescription": null,
      "abortReason": null,
      "auctionRefNo": [],
      "amendsNoticeRefNo": [],
      "cpv_codes_extracted": [
        "03221320"
      ],
      "cpv_divisions": [
        "03"
      ],
      "all_domains": [
        "Agriculture & Forestry"
      ],
      "primary_domain": "Agriculture & Forestry"
    }
  ]
}