{
  "domain": "Education & Training",
  "count": 7,
  "items": [
    {
      "title": "ΠΡΟΣΚΛΗΣΗ ΥΠΟΒΟΛΗΣ ΠΡΟΣΦΟΡΑΣ ΠΑΡΟΧΗΣ ΥΠΗΡΕΣΙΩΝ ΕΚΠΑΙΔΕΥΣΗΣ",
      "referenceNumber": "26PROC018460395",
      "signedDate": "2026-02-10T00:00:00",
      "publishedDate": null,
      "finalSubmissionDate": "2026-02-16T17:00:00",
      "submissionDate": "2026-02-10T21:35:49.617",
      "lastUpdateDate": null,
      "cancelled": false,
      "cancellationDate": null,
      "cancellationType": null,
      "cancellationReason": null,
      "cancellationADA": null,
      "amendPreviousNotice": false,
      "amendedNoticeADAM": null,
      "frameworkAgreementNoticeADAM": null,
      "protocolNumber": null,
      "authorEmail": null,
      "aaht": "1031.E00930.0001",
      "biddingWebsite": null,
      "organizationVatNumber": null,
      "greekOrganizationVatNumber": null,
      "budget": null,
      "commitmentNo": null,
      "relatedNoticeADAM": null,
      "numberOfSections": 1,
      "nutsCode": {
        "key": "EL303",
        "value": "Κεντρικός Τομέας Αθηνών"
      },
      "nutsCity": "ΑΘΗΝΑ",
      "nutsPostalCode": "11525",
      "nutsCountry": {
        "key": "GR",
        "value": "Ελλάδα"
      },
      "assignedContract": {
        "key": "2",
        "value": "Όχι"
      },
      "socialContract": {
        "key": "2",
        "value": "Όχι"
      },
      "centralGovernmentAuthority": {
        "key": "2",
        "value": "Όχι"
      },
      "contractingData": {
        "unitsOperator": {
          "key": "100013181",
          "value": "ΔΙΟΙΚΗΣΗ"
        },
        "signers": {
          "key": "100061521",
          "value": "ΑΡΙΣΤΟΦΑΝΗΣ ΣΤΕΦΑΤΟΣ - Διευθύνων Σύμβουλος"
        }
      },
      "fundingDetails": {
        "publicFundingRef": null,
        "publicFundingRefNum": null,
        "publicFundingRefOps": null,
        "cofundProgramRef": null,
        "selfFundProgramRef": null,
        "espaFundProgramRef": null,
        "regularBudgetFundedProgramRef": "61"
      },
      "systemicNumbers": [],
      "approvedRequests": [
        {
          "code": "26REQ018460394"
        }
      ],
      "contractingAuthorities": [
        {
          "contractingAuthority": {
            "key": "10",
            "value": "ΝΠΙΔ"
          }
        }
      ],
      "nutsCodes": [
        {
          "nutsCode": {
            "key": "EL303",
            "value": "Κεντρικός Τομέας Αθηνών"
          }
        }
      ],
      "organization": {
        "key": "100013141",
        "value": "ΕΛΛΗΝΙΚΗ ΔΙΑΧΕΙΡΙΣΤΙΚΗ ΕΤΑΙΡΙΑ ΥΔΡΟΓΟΝΑΝΘΡΑΚΩΝ ΑΕ"
      },
      "typeOfProcedure": {
        "key": "6",
        "value": "Απευθείας ανάθεση"
      },
      "contractType": {
        "key": "9",
        "value": "Υπηρεσίες"
      },
      "awardProcedure": null,
      "centralizedMarkets": [
        {
          "centralizedMarket": {
            "key": "8",
            "value": "Δεν χρησιμοποιείται"
          }
        }
      ],
      "legalContext": {
        "key": "5",
        "value": "ν.4412/2016 - Βιβλίο Ι – κάτω των ορίων"
      },
      "conductingProceedings": {
        "key": "2",
        "value": "Μη ηλεκτρονική διαδικασία"
      },
      "digitalPlatform": null,
      "criteriaCode": {
        "key": "4",
        "value": "Βάσει κόστους – άλλο"
      },
      "classificationOfPublicLawOrganization": {
        "key": "4",
        "value": "Εκτός Γενικής Κυβέρνησης"
      },
      "noticeType": {
        "key": "4",
        "value": "Πρόσκληση"
      },
      "contractingAuthorityActivity": {
        "key": "12",
        "value": "Τυχόν άλλη δραστηριότητα"
      },
      "contractDuration": 3,
      "contractDurationUnitOfMeasure": {
        "key": "3",
        "value": "Μήνες"
      },
      "totalCostWithVAT": 8146.8,
      "totalCostWithoutVAT": 6570.0,
      "objectDetails": [
        {
          "quantity": 1,
          "type": {
            "key": "E48",
            "value": "Υπηρεσία"
          },
          "costWithoutVAT": 6570,
          "vat": "24",
          "currency": {
            "key": "EUR",
            "value": "Ευρώ"
          },
          "shortDescription": "ΠΡΟΣΚΛΗΣΗ ΥΠΟΒΟΛΗΣ ΠΡΟΣΦΟΡΑΣ ΠΑΡΟΧΗΣ ΥΠΗΡΕΣΙΩΝ ΕΚΠΑΙΔΕΥΣΗΣ",
          "cpvs": [
            {
              "key": "80532000-2",
              "value": "Υπηρεσίες εκπαίδευσης στον τομέα της διαχείρισης"
            }
          ],
          "greenContracts": {
            "key": "1",
            "value": "Δεν εμπίπτει στο ΕΣΔ"
          },
          "goodServices": null,
          "budgetCode": null
        }
      ],
      "additionalContractTypes": null,
      "mixedContract": false,
      "offersValidTime": 3,
      "offersValidTimeUnitOfMeasure": {
        "key": "3",
        "value": "Μήνες"
      },
      "maxNumberOfContractors": null,
      "optionRight": {
        "key": "2",
        "value": "Όχι"
      },
      "optionRightDescription": null,
      "abortReason": null,
      "auctionRefNo": [],
      "amendsNoticeRefNo": [],
      "cpv_codes_extracted": [
        "80532000"
      ],
      "cpv_divisions": [
        "80"
      ],
      "all_domains": [
        "Education & Training"
      ],
      "primary_domain": "Education & Training"
    },
    {
      "title": "ΠΡΟΣΚΛΗΣΗ ΥΠΟΒΟΛΗΣ ΠΡΟΣΦΟΡΑΣ ΠΑΡΟΧΗΣ ΥΠΗΡΕΣΙΩΝ ΕΚΠΑΙΔΕΥΣΗΣ",
      "referenceNumber": "26PROC018459272",
      "signedDate": "2026-02-10T00:00:00",
      "publishedDate": null,
      "finalSubmissionDate": "2026-02-16T18:00:00",
      "submissionDate": "2026-02-10T14:18:15.405",
      "lastUpdateDate": "2026-02-10T21:18:58.006",
      "cancelled": true,
      "cancellationDate": "2026-02-10T21:18:58.006",
      "cancellationType": "Ακύρωση λόγω λανθασμένης καταχώρησης",
      "cancellationReason": "ΛΑΝΘΑΣΜΕΝΗ ΚΑΤΑΧΩΡΗΣΗ",
      "cancellationADA": null,
      "amendPreviousNotice": false,
      "amendedNoticeADAM": null,
      "frameworkAgreementNoticeADAM": null,
      "protocolNumber": null,
      "authorEmail": null,
      "aaht": "1031.E00930.0001",
      "biddingWebsite": null,
      "organizationVatNumber": null,
      "greekOrganizationVatNumber": null,
      "budget": null,
      "commitmentNo": null,
      "relatedNoticeADAM": null,
      "numberOfSections": 1,
      "nutsCode": {
        "key": "EL303",
        "value": "Κεντρικός Τομέας Αθηνών"
      },
      "nutsCity": "ΑΘΗΝΑ",
      "nutsPostalCode": "11525",
      "nutsCountry": {
        "key": "GR",
        "value": "Ελλάδα"
      },
      "assignedContract": {
        "key": "2",
        "value": "Όχι"
      },
      "socialContract": {
        "key": "2",
        "value": "Όχι"
      },
      "centralGovernmentAuthority": {
        "key": "2",
        "value": "Όχι"
      },
      "contractingData": {
        "unitsOperator": {
          "key": "100013181",
          "value": "ΔΙΟΙΚΗΣΗ"
        },
        "signers": {
          "key": "100061521",
          "value": "ΑΡΙΣΤΟΦΑΝΗΣ ΣΤΕΦΑΤΟΣ - Διευθύνων Σύμβουλος"
        }
      },
      "fundingDetails": {
        "publicFundingRef": null,
        "publicFundingRefNum": null,
        "publicFundingRefOps": null,
        "cofundProgramRef": null,
        "selfFundProgramRef": null,
        "espaFundProgramRef": null,
        "regularBudgetFundedProgramRef": "64"
      },
      "systemicNumbers": [],
      "approvedRequests": [
        {
          "code": "26REQ018459107"
        }
      ],
      "contractingAuthorities": [
        {
          "contractingAuthority": {
            "key": "10",
            "value": "ΝΠΙΔ"
          }
        }
      ],
      "nutsCodes": [
        {
          "nutsCode": {
            "key": "EL303",
            "value": "Κεντρικός Τομέας Αθηνών"
          }
        }
      ],
      "organization": {
        "key": "100013141",
        "value": "ΕΛΛΗΝΙΚΗ ΔΙΑΧΕΙΡΙΣΤΙΚΗ ΕΤΑΙΡΙΑ ΥΔΡΟΓΟΝΑΝΘΡΑΚΩΝ ΑΕ"
      },
      "typeOfProcedure": {
        "key": "6",
        "value": "Απευθείας ανάθεση"
      },
      "contractType": {
        "key": "9",
        "value": "Υπηρεσίες"
      },
      "awardProcedure": null,
      "centralizedMarkets": [
        {
          "centralizedMarket": {
            "key": "8",
            "value": "Δεν χρησιμοποιείται"
          }
        }
      ],
      "legalContext": {
        "key": "5",
        "value": "ν.4412/2016 - Βιβλίο Ι – κάτω των ορίων"
      },
      "conductingProceedings": {
        "key": "2",
        "value": "Μη ηλεκτρονική διαδικασία"
      },
      "digitalPlatform": null,
      "criteriaCode": {
        "key": "4",
        "value": "Βάσει κόστους – άλλο"
      },
      "classificationOfPublicLawOrganization": {
        "key": "4",
        "value": "Εκτός Γενικής Κυβέρνησης"
      },
      "noticeType": {
        "key": "4",
        "value": "Πρόσκληση"
      },
      "contractingAuthorityActivity": {
        "key": "12",
        "value": "Τυχόν άλλη δραστηριότητα"
      },
      "contractDuration": 3,
      "contractDurationUnitOfMeasure": {
        "key": "3",
        "value": "Μήνες"
      },
      "totalCostWithVAT": 8109.6,
      "totalCostWithoutVAT": 6540.0,
      "objectDetails": [
        {
          "quantity": 1,
          "type": {
            "key": "E48",
            "value": "Υπηρεσία"
          },
          "costWithoutVAT": 6540,
          "vat": "24",
          "currency": {
            "key": "EUR",
            "value": "Ευρώ"
          },
          "shortDescription": "ΠΡΟΣΚΛΗΣΗ ΥΠΟΒΟΛΗΣ ΠΡΟΣΦΟΡΑΣ ΠΑΡΟΧΗΣ ΥΠΗΡΕΣΙΩΝ ΕΚΠΑΙΔΕΥΣΗΣ",
          "cpvs": [
            {
              "key": "80532000-2",
              "value": "Υπηρεσίες εκπαίδευσης στον τομέα της διαχείρισης"
            }
          ],
          "greenContracts": {
            "key": "1",
            "value": "Δεν εμπίπτει στο ΕΣΔ"
          },
          "goodServices": null,
          "budgetCode": null
        }
      ],
      "additionalContractTypes": null,
      "mixedContract": false,
      "offersValidTime": 3,
      "offersValidTimeUnitOfMeasure": {
        "key": "3",
        "value": "Μήνες"
      },
      "maxNumberOfContractors": null,
      "optionRight": {
        "key": "2",
        "value": "Όχι"
      },
      "optionRightDescription": null,
      "abortReason": null,
      "auctionRefNo": [],
      "amendsNoticeRefNo": [],
      "cpv_codes_extracted": [
        "80532000"
      ],
      "cpv_divisions": [
        "80"
      ],
      "all_domains": [
        "Education & Training"
      ],
      "primary_domain": "Education & Training"
    },
    {
      "title": "ΥΠΡ002.26_ΣΕΜΙΝΑΡΙΟ ΚΑΤΑΡΤΙΣΗΣ ΠΛΗΡΟΦΟΡΙΑΚΟΥ ΣΥΣΤΗΜΑΤΟΣ e-PDE",
      "referenceNumber": "26PROC018454856",
      "signedDate": "2026-02-10T00:00:00",
      "publishedDate": null,
      "finalSubmissionDate": "2026-02-17T23:59:00",
      "submissionDate": "2026-02-10T09:53:13.99",
      "lastUpdateDate": null,
      "cancelled": false,
      "cancellationDate": null,
      "cancellationType": null,
      "cancellationReason": null,
      "cancellationADA": null,
      "amendPreviousNotice": false,
      "amendedNoticeADAM": null,
      "frameworkAgreementNoticeADAM": null,
      "protocolNumber": null,
      "authorEmail": null,
      "aaht": "1007.F00872.0001",
      "biddingWebsite": null,
      "organizationVatNumber": null,
      "greekOrganizationVatNumber": null,
      "budget": null,
      "commitmentNo": null,
      "relatedNoticeADAM": null,
      "numberOfSections": 1,
      "nutsCode": {
        "key": "EL421",
        "value": "Κάλυμνος, Κάρπαθος, Κως, Ρόδος"
      },
      "nutsCity": "ΡΟΔΟΣ",
      "nutsPostalCode": "85100",
      "nutsCountry": {
        "key": "GR",
        "value": "Ελλάδα"
      },
      "assignedContract": {
        "key": "2",
        "value": "Όχι"
      },
      "socialContract": {
        "key": "2",
        "value": "Όχι"
      },
      "centralGovernmentAuthority": {
        "key": "2",
        "value": "Όχι"
      },
      "contractingData": {
        "unitsOperator": {
          "key": "86178",
          "value": "ΔΙΟΙΚΗΤΙΚΟ ΣΥΜΒΟΥΛΙΟ"
        },
        "signers": {
          "key": "100087238",
          "value": "ΣΩΤΗΡΙΟΣ ΒΑΓΙΑΝΟΣ - Πρόεδρος Δ.Σ."
        }
      },
      "fundingDetails": {
        "publicFundingRef": null,
        "publicFundingRefNum": null,
        "publicFundingRefOps": null,
        "cofundProgramRef": null,
        "selfFundProgramRef": "60.00.02.04",
        "espaFundProgramRef": null,
        "regularBudgetFundedProgramRef": null
      },
      "systemicNumbers": [],
      "approvedRequests": [
        {
          "code": "26REQ018453515"
        }
      ],
      "contractingAuthorities": [
        {
          "contractingAuthority": {
            "key": "10",
            "value": "ΝΠΙΔ"
          }
        }
      ],
      "nutsCodes": [
        {
          "nutsCode": {
            "key": "EL421",
            "value": "Κάλυμνος, Κάρπαθος, Κως, Ρόδος"
          }
        }
      ],
      "organization": {
        "key": "52826",
        "value": "ΔΗΜΟΤΙΚΗ ΕΠΙΧΕΙΡΗΣΗ ΥΔΡΕΥΣΗΣ ΑΠΟΧΕΤΕΥΣΗΣ ΔΗΜΟΥ ΡΟΔΟΥ (Δ.Ε.Υ.ΑΡ)"
      },
      "typeOfProcedure": {
        "key": "6",
        "value": "Απευθείας ανάθεση"
      },
      "contractType": {
        "key": "9",
        "value": "Υπηρεσίες"
      },
      "awardProcedure": null,
      "centralizedMarkets": [
        {
          "centralizedMarket": {
            "key": "8",
            "value": "Δεν χρησιμοποιείται"
          }
        }
      ],
      "legalContext": {
        "key": "7",
        "value": "ν.4412/2016 - Βιβλίο ΙΙ – κάτω των ορίων"
      },
      "conductingProceedings": {
        "key": "2",
        "value": "Μη ηλεκτρονική διαδικασία"
      },
      "digitalPlatform": null,
      "criteriaCode": {
        "key": "2",
        "value": "Βάσει τιμής"
      },
      "classificationOfPublicLawOrganization": {
        "key": "2",
        "value": "ΟΤΑ"
      },
      "noticeType": {
        "key": "4",
        "value": "Πρόσκληση"
      },
      "contractingAuthorityActivity": {
        "key": "7",
        "value": "Στέγαση και υποδομές κοινής ωφέλειας"
      },
      "contractDuration": 3,
      "contractDurationUnitOfMeasure": {
        "key": "3",
        "value": "Μήνες"
      },
      "totalCostWithVAT": 840.0,
      "totalCostWithoutVAT": 840.0,
      "objectDetails": [
        {
          "quantity": 1,
          "type": {
            "key": "E48",
            "value": "Υπηρεσία"
          },
          "costWithoutVAT": 840,
          "vat": "0",
          "currency": {
            "key": "EUR",
            "value": "Ευρώ"
          },
          "shortDescription": "ΥΠΡ002.26_ΣΕΜΙΝΑΡΙΟ ΚΑΤΑΡΤΙΣΗΣ ΠΛΗΡΟΦΟΡΙΑΚΟΥ ΣΥΣΤΗΜΑΤΟΣ e-PDE",
          "cpvs": [
            {
              "key": "80500000-9",
              "value": "Υπηρεσίες κατάρτισης"
            }
          ],
          "greenContracts": {
            "key": "1",
            "value": "Δεν εμπίπτει στο ΕΣΔ"
          },
          "goodServices": null,
          "budgetCode": null
        }
      ],
      "additionalContractTypes": null,
      "mixedContract": false,
      "offersValidTime": 12,
      "offersValidTimeUnitOfMeasure": {
        "key": "3",
        "value": "Μήνες"
      },
      "maxNumberOfContractors": null,
      "optionRight": {
        "key": "2",
        "value": "Όχι"
      },
      "optionRightDescription": null,
      "abortReason": null,
      "auctionRefNo": [],
      "amendsNoticeRefNo": [],
      "cpv_codes_extracted": [
        "80500000"
      ],
      "cpv_divisions": [
        "80"
      ],
      "all_domains": [
        "Education & Training"
      ],
      "primary_domain": "Education & Training"
    },
    {
      "title": "Πρόσκληση υποβολής οικονομικής προσφοράς για τη συμμετοχή υπαλλήλων του ΕΟΤ σε επιμορφωτικό συνέδριο",
      "referenceNumber": "26PROC018454627",
      "signedDate": "2026-02-10T00:00:00",
      "publishedDate": null,
      "finalSubmissionDate": "2026-02-13T23:59:00",
      "submissionDate": "2026-02-10T09:36:49.34",
      "lastUpdateDate": null,
      "cancelled": false,
      "cancellationDate": null,
      "cancellationType": null,
      "cancellationReason": null,
      "cancellationADA": null,
      "amendPreviousNotice": false,
      "amendedNoticeADAM": null,
      "frameworkAgreementNoticeADAM": null,
      "protocolNumber": null,
      "authorEmail": null,
      "aaht": "1045.Ε00800.0001",
      "biddingWebsite": null,
      "organizationVatNumber": null,
      "greekOrganizationVatNumber": null,
      "budget": null,
      "commitmentNo": null,
      "relatedNoticeADAM": null,
      "numberOfSections": 1,
      "nutsCode": {
        "key": "EL",
        "value": "ΕΛΛΑΔΑ"
      },
      "nutsCity": "Αθήνα",
      "nutsPostalCode": "11521",
      "nutsCountry": {
        "key": "GR",
        "value": "Ελλάδα"
      },
      "assignedContract": {
        "key": "2",
        "value": "Όχι"
      },
      "socialContract": {
        "key": "2",
        "value": "Όχι"
      },
      "centralGovernmentAuthority": {
        "key": "2",
        "value": "Όχι"
      },
      "contractingData": {
        "unitsOperator": {
          "key": "100041922",
          "value": "ΔΙΟΙΚΗΤΙΚΩΝ ΥΠΗΡΕΣΙΩΝ"
        },
        "signers": {
          "key": "100096877",
          "value": "ΠΑΝΑΓΙΩΤΑ ΧΑΡΙΤΟΥ - Αναπληρωτής Διευθυντής"
        }
      },
      "fundingDetails": {
        "publicFundingRef": null,
        "publicFundingRefNum": null,
        "publicFundingRefOps": null,
        "cofundProgramRef": null,
        "selfFundProgramRef": null,
        "espaFundProgramRef": null,
        "regularBudgetFundedProgramRef": "2420909"
      },
      "systemicNumbers": [],
      "approvedRequests": [
        {
          "code": "26REQ018449162"
        }
      ],
      "contractingAuthorities": [
        {
          "contractingAuthority": {
            "key": "9",
            "value": "ΝΠΔΔ"
          }
        }
      ],
      "nutsCodes": [
        {
          "nutsCode": {
            "key": "EL303",
            "value": "Κεντρικός Τομέας Αθηνών"
          }
        }
      ],
      "organization": {
        "key": "99221315",
        "value": "ΕΛΛΗΝΙΚΟΣ ΟΡΓΑΝΙΣΜΟΣ ΤΟΥΡΙΣΜΟΥ (ΕΟΤ)"
      },
      "typeOfProcedure": {
        "key": "6",
        "value": "Απευθείας ανάθεση"
      },
      "contractType": {
        "key": "9",
        "value": "Υπηρεσίες"
      },
      "awardProcedure": null,
      "centralizedMarkets": [
        {
          "centralizedMarket": {
            "key": "8",
            "value": "Δεν χρησιμοποιείται"
          }
        }
      ],
      "legalContext": {
        "key": "5",
        "value": "ν.4412/2016 - Βιβλίο Ι – κάτω των ορίων"
      },
      "conductingProceedings": {
        "key": "2",
        "value": "Μη ηλεκτρονική διαδικασία"
      },
      "digitalPlatform": null,
      "criteriaCode": {
        "key": "4",
        "value": "Βάσει κόστους – άλλο"
      },
      "classificationOfPublicLawOrganization": {
        "key": "1",
        "value": "Κεντρική Κυβέρνηση"
      },
      "noticeType": {
        "key": "4",
        "value": "Πρόσκληση"
      },
      "contractingAuthorityActivity": {
        "key": "12",
        "value": "Τυχόν άλλη δραστηριότητα"
      },
      "contractDuration": 1,
      "contractDurationUnitOfMeasure": {
        "key": "3",
        "value": "Μήνες"
      },
      "totalCostWithVAT": 2157.6,
      "totalCostWithoutVAT": 1740.0,
      "objectDetails": [
        {
          "quantity": 1,
          "type": {
            "key": "E48",
            "value": "Υπηρεσία"
          },
          "costWithoutVAT": 1740,
          "vat": "24",
          "currency": {
            "key": "EUR",
            "value": "Ευρώ"
          },
          "shortDescription": "ΥΣ Δέσμευσης Πίστωσης για Συμμετοχή 10 Υπαλλήλων της Διεύθυνσης Τουριστικής Προβολής του ΕΟΤ στο επιμορφωτικό συνέδριο All Things Facebook & Instagram Conference 2026: Mastering the Full-Funnel Power of Meta, της εταιρείας Κλαδικές Εκδηλώσεις ΙΚΕ ",
          "cpvs": [
            {
              "key": "80511000-9",
              "value": "Υπηρεσίες επιμόρφωσης προσωπικού"
            }
          ],
          "greenContracts": {
            "key": "1",
            "value": "Δεν εμπίπτει στο ΕΣΔ"
          },
          "goodServices": null,
          "budgetCode": null
        }
      ],
      "additionalContractTypes": null,
      "mixedContract": false,
      "offersValidTime": 10,
      "offersValidTimeUnitOfMeasure": {
        "key": "1",
        "value": "Ημέρες"
      },
      "maxNumberOfContractors": null,
      "optionRight": {
        "key": "2",
        "value": "Όχι"
      },
      "optionRightDescription": null,
      "abortReason": null,
      "auctionRefNo": [],
      "amendsNoticeRefNo": [],
      "cpv_codes_extracted": [
        "99221315",
        "80511000"
      ],
      "cpv_divisions": [
        "80"
      ],
      "all_domains": [
        "Education & Training"
      ],
      "primary_domain": "Education & Training"
    },
    {
      "title": "Προκήρυξη διαγωνισμού για \"Δράσεις Ψηφιακού Μετασχηματισμού Δήμου Ξάνθης\"",
      "referenceNumber": "26PROC018453874",
      "signedDate": "2026-02-04T00:00:00",
      "publishedDate": "2026-02-06T00:00:00",
      "finalSubmissionDate": "2026-03-16T15:00:00",
      "submissionDate": "2026-02-10T08:36:14.306",
      "lastUpdateDate": null,
      "cancelled": false,
      "cancellationDate": null,
      "cancellationType": null,
      "cancellationReason": null,
      "cancellationADA": null,
      "amendPreviousNotice": false,
      "amendedNoticeADAM": null,
      "frameworkAgreementNoticeADAM": null,
      "protocolNumber": null,
      "authorEmail": null,
      "aaht": "1007.Ε80601.0001",
      "biddingWebsite": "https://nepps.eprocurement.gov.gr/",
      "organizationVatNumber": null,
      "greekOrganizationVatNumber": null,
      "budget": null,
      "commitmentNo": null,
      "relatedNoticeADAM": null,
      "numberOfSections": 2,
      "nutsCode": {
        "key": "EL512",
        "value": "Ξάνθη"
      },
      "nutsCity": "Ξάνθη",
      "nutsPostalCode": "67132",
      "nutsCountry": {
        "key": "GR",
        "value": "Ελλάδα"
      },
      "assignedContract": {
        "key": "2",
        "value": "Όχι"
      },
      "socialContract": {
        "key": "2",
        "value": "Όχι"
      },
      "centralGovernmentAuthority": {
        "key": "2",
        "value": "Όχι"
      },
      "contractingData": {
        "unitsOperator": {
          "key": "93861",
          "value": "ΔΙΕΥΘΥΝΣΗ ΟΙΚΟΝΟΜΙΚΩΝ ΥΠΗΡΕΣΙΩΝ"
        },
        "signers": {
          "key": "100048749",
          "value": "ΣΙΑΜΠΑΝ ΜΠΑΝΤΑΚ - Αντιδήμαρχος"
        }
      },
      "fundingDetails": {
        "publicFundingRef": "Ε2637",
        "publicFundingRefNum": "2025ΣΕ26370105",
        "publicFundingRefOps": "6003079",
        "cofundProgramRef": null,
        "selfFundProgramRef": null,
        "espaFundProgramRef": null,
        "regularBudgetFundedProgramRef": null
      },
      "systemicNumbers": [
        {
          "systemicNumber": "398081"
        },
        {
          "systemicNumber": "398101"
        }
      ],
      "approvedRequests": [
        {
          "code": "25REQ018241030"
        }
      ],
      "contractingAuthorities": [
        {
          "contractingAuthority": {
            "key": "9",
            "value": "ΝΠΔΔ"
          }
        }
      ],
      "nutsCodes": [
        {
          "nutsCode": {
            "key": "EL512",
            "value": "Ξάνθη"
          }
        }
      ],
      "organization": {
        "key": "6220",
        "value": "ΔΗΜΟΣ ΞΑΝΘΗΣ"
      },
      "typeOfProcedure": {
        "key": "1",
        "value": "Ανοιχτή διαδικασία"
      },
      "contractType": {
        "key": "13",
        "value": "Προμήθειες"
      },
      "awardProcedure": null,
      "centralizedMarkets": [
        {
          "centralizedMarket": {
            "key": "8",
            "value": "Δεν χρησιμοποιείται"
          }
        }
      ],
      "legalContext": {
        "key": "4",
        "value": "ν.4412/2016 - Βιβλίο Ι – άνω των ορίων"
      },
      "conductingProceedings": {
        "key": "1",
        "value": "Ηλεκτρονική Διαδικασία"
      },
      "digitalPlatform": {
        "key": "3",
        "value": "ΕΣΗΔΗΣ ΠΥ"
      },
      "criteriaCode": {
        "key": "1",
        "value": "Βάσει κόστους – βέλτιστη σχέση ποιότητας – τιμής"
      },
      "classificationOfPublicLawOrganization": {
        "key": "2",
        "value": "ΟΤΑ"
      },
      "noticeType": {
        "key": "2",
        "value": "Προκήρυξη"
      },
      "contractingAuthorityActivity": {
        "key": "1",
        "value": "Γενικές δημόσιες υπηρεσίες"
      },
      "contractDuration": 18,
      "contractDurationUnitOfMeasure": {
        "key": "3",
        "value": "Μήνες"
      },
      "totalCostWithVAT": 588721.35,
      "totalCostWithoutVAT": 474775.28,
      "objectDetails": [
        {
          "quantity": 1,
          "type": {
            "key": "AG-001",
            "value": "Μελέτη"
          },
          "costWithoutVAT": 264528.02,
          "vat": "24",
          "currency": {
            "key": "EUR",
            "value": "Ευρώ"
          },
          "shortDescription": "Προκήρυξη διαγωνισμού που αφορά στο Υποέργο 2 της Πράξης «Ανάπτυξη Εφαρμογών Έξυπνων Πόλεων και Τεχνολογιών για το Διαδίκτυο των Αντικειμένων (ΙΟΤ) του Δήμου Ξάνθης » (ΜΙS 6003079) και συγχρηματοδοτείται από το Ευρωπαϊκό Ταμείο Περιφερειακής Ανάπτυξης για ΤΜΗΜΑ 1: «ΔΡΑΣΕΙΣ ΨΗΦΙΑΚΟΥ ΜΕΤΑΣΧΗΜΑΤΙΣΜΟΥ ΠΛΗΝ ΟΙΚΟΝΟΜΙΚΗΣ ΔΙΑΧΕΙΡΙΣΗΣ ΚΑΙ ΠΛΗΝ ΔΙΑΧΕΙΡΙΣΗΣ ΕΠΙΧΕΙΡΗΣΙΑΚΩΝ ΔΙΑΔΙΚΑΣΙΩΝ»",
          "cpvs": [
            {
              "key": "80533100-0",
              "value": "Υπηρεσίες εκπαίδευσης στον τομέα της πληροφορικής"
            },
            {
              "key": "48600000-4",
              "value": "Πακέτα λογισμικού βάσεων δεδομένων και λειτουργικών συστημάτων"
            },
            {
              "key": "72254100-1",
              "value": "Υπηρεσίες δοκιμής συστημάτων πληροφορικής"
            },
            {
              "key": "79131000-1",
              "value": "Υπηρεσίες τεκμηρίωσης"
            }
          ],
          "greenContracts": {
            "key": "1",
            "value": "Δεν εμπίπτει στο ΕΣΔ"
          },
          "goodServices": null,
          "budgetCode": null
        },
        {
          "quantity": 1,
          "type": {
            "key": "AG-001",
            "value": "Μελέτη"
          },
          "costWithoutVAT": 210247.26,
          "vat": "24",
          "currency": {
            "key": "EUR",
            "value": "Ευρώ"
          },
          "shortDescription": "Προκήρυξη διαγωνισμού που αφορά στο Υποέργο 2 της Πράξης «Ανάπτυξη Εφαρμογών Έξυπνων Πόλεων και Τεχνολογιών για το Διαδίκτυο των Αντικειμένων (ΙΟΤ) του Δήμου Ξάνθης » (ΜΙS 6003079) και συγχρηματοδοτείται από το Ευρωπαϊκό Ταμείο Περιφερειακής Ανάπτυξης για ΤΜΗΜΑ 2: «ΔΡΑΣΕΙΣ ΟΙΚΟΝΟΜΙΚΗΣ ΔΙΑΧΕΙΡΙΣΗΣ ΚΑΙ ΔΙΑΧΕΙΡΙΣΗΣ ΕΠΙΧΕΙΡΗΣΙΑΚΩΝ ΔΙΑΔΙΚΑΣΙΩΝ»",
          "cpvs": [
            {
              "key": "79999100-4",
              "value": "Υπηρεσίες σάρωσης"
            },
            {
              "key": "72254100-1",
              "value": "Υπηρεσίες δοκιμής συστημάτων πληροφορικής"
            },
            {
              "key": "80533100-0",
              "value": "Υπηρεσίες εκπαίδευσης στον τομέα της πληροφορικής"
            },
            {
              "key": "79131000-1",
              "value": "Υπηρεσίες τεκμηρίωσης"
            },
            {
              "key": "48600000-4",
              "value": "Πακέτα λογισμικού βάσεων δεδομένων και λειτουργικών συστημάτων"
            }
          ],
          "greenContracts": {
            "key": "1",
            "value": "Δεν εμπίπτει στο ΕΣΔ"
          },
          "goodServices": null,
          "budgetCode": null
        }
      ],
      "additionalContractTypes": [
        {
          "additionalContractType": {
            "key": "3",
            "value": "Υπηρεσίες"
          }
        }
      ],
      "mixedContract": true,
      "offersValidTime": 12,
      "offersValidTimeUnitOfMeasure": {
        "key": "3",
        "value": "Μήνες"
      },
      "maxNumberOfContractors": null,
      "optionRight": {
        "key": "2",
        "value": "Όχι"
      },
      "optionRightDescription": null,
      "abortReason": null,
      "auctionRefNo": [],
      "amendsNoticeRefNo": [],
      "cpv_codes_extracted": [
        "80533100",
        "48600000",
        "72254100",
        "79131000",
        "79999100"
      ],
      "cpv_divisions": [
        "80",
        "48",
        "72",
        "79"
      ],
      "all_domains": [
        "Education & Training",
        "Software & Information Systems",
        "IT Services",
        "Business Services (Legal/Marketing/Recruitment/Security/Print)"
      ],
      "primary_domain": "Software & Information Systems"
    },
    {
      "title": "Διακήρυξη διαγωνισμού για Δράσεις Ψηφιακού Μετασχηματισμού Δήμου Ξάνθης",
      "referenceNumber": "26PROC018453852",
      "signedDate": "2026-02-04T00:00:00",
      "publishedDate": "2026-02-06T00:00:00",
      "finalSubmissionDate": "2026-03-16T15:00:00",
      "submissionDate": "2026-02-10T08:34:21.805",
      "lastUpdateDate": null,
      "cancelled": false,
      "cancellationDate": null,
      "cancellationType": null,
      "cancellationReason": null,
      "cancellationADA": null,
      "amendPreviousNotice": false,
      "amendedNoticeADAM": null,
      "frameworkAgreementNoticeADAM": null,
      "protocolNumber": null,
      "authorEmail": null,
      "aaht": "1007.Ε80601.0001",
      "biddingWebsite": "https://nepps.eprocurement.gov.gr/",
      "organizationVatNumber": null,
      "greekOrganizationVatNumber": null,
      "budget": null,
      "commitmentNo": null,
      "relatedNoticeADAM": null,
      "numberOfSections": 2,
      "nutsCode": {
        "key": "EL512",
        "value": "Ξάνθη"
      },
      "nutsCity": "Ξάνθη",
      "nutsPostalCode": "67132",
      "nutsCountry": {
        "key": "GR",
        "value": "Ελλάδα"
      },
      "assignedContract": {
        "key": "2",
        "value": "Όχι"
      },
      "socialContract": {
        "key": "2",
        "value": "Όχι"
      },
      "centralGovernmentAuthority": {
        "key": "2",
        "value": "Όχι"
      },
      "contractingData": {
        "unitsOperator": {
          "key": "93861",
          "value": "ΔΙΕΥΘΥΝΣΗ ΟΙΚΟΝΟΜΙΚΩΝ ΥΠΗΡΕΣΙΩΝ"
        },
        "signers": {
          "key": "100048749",
          "value": "ΣΙΑΜΠΑΝ ΜΠΑΝΤΑΚ - Αντιδήμαρχος"
        }
      },
      "fundingDetails": {
        "publicFundingRef": "Ε2637",
        "publicFundingRefNum": "2025ΣΕ26370105",
        "publicFundingRefOps": "6003079",
        "cofundProgramRef": null,
        "selfFundProgramRef": null,
        "espaFundProgramRef": null,
        "regularBudgetFundedProgramRef": null
      },
      "systemicNumbers": [
        {
          "systemicNumber": "398101"
        },
        {
          "systemicNumber": "398081"
        }
      ],
      "approvedRequests": [
        {
          "code": "25REQ018241030"
        }
      ],
      "contractingAuthorities": [
        {
          "contractingAuthority": {
            "key": "9",
            "value": "ΝΠΔΔ"
          }
        }
      ],
      "nutsCodes": [
        {
          "nutsCode": {
            "key": "EL512",
            "value": "Ξάνθη"
          }
        }
      ],
      "organization": {
        "key": "6220",
        "value": "ΔΗΜΟΣ ΞΑΝΘΗΣ"
      },
      "typeOfProcedure": {
        "key": "1",
        "value": "Ανοιχτή διαδικασία"
      },
      "contractType": {
        "key": "13",
        "value": "Προμήθειες"
      },
      "awardProcedure": null,
      "centralizedMarkets": [
        {
          "centralizedMarket": {
            "key": "8",
            "value": "Δεν χρησιμοποιείται"
          }
        }
      ],
      "legalContext": {
        "key": "4",
        "value": "ν.4412/2016 - Βιβλίο Ι – άνω των ορίων"
      },
      "conductingProceedings": {
        "key": "1",
        "value": "Ηλεκτρονική Διαδικασία"
      },
      "digitalPlatform": {
        "key": "3",
        "value": "ΕΣΗΔΗΣ ΠΥ"
      },
      "criteriaCode": {
        "key": "1",
        "value": "Βάσει κόστους – βέλτιστη σχέση ποιότητας – τιμής"
      },
      "classificationOfPublicLawOrganization": {
        "key": "2",
        "value": "ΟΤΑ"
      },
      "noticeType": {
        "key": "3",
        "value": "Διακήρυξη"
      },
      "contractingAuthorityActivity": {
        "key": "1",
        "value": "Γενικές δημόσιες υπηρεσίες"
      },
      "contractDuration": 18,
      "contractDurationUnitOfMeasure": {
        "key": "3",
        "value": "Μήνες"
      },
      "totalCostWithVAT": 588721.35,
      "totalCostWithoutVAT": 474775.28,
      "objectDetails": [
        {
          "quantity": 1,
          "type": {
            "key": "AG-001",
            "value": "Μελέτη"
          },
          "costWithoutVAT": 264528.02,
          "vat": "24",
          "currency": {
            "key": "EUR",
            "value": "Ευρώ"
          },
          "shortDescription": "Διακήρυξη διαγωνισμού που αφορά στο Υποέργο 2 της Πράξης «Ανάπτυξη Εφαρμογών Έξυπνων Πόλεων και Τεχνολογιών για το Διαδίκτυο των Αντικειμένων (ΙΟΤ) του Δήμου Ξάνθης » (ΜΙS 6003079) και συγχρηματοδοτείται από το Ευρωπαϊκό Ταμείο Περιφερειακής Ανάπτυξης για ΤΜΗΜΑ 1: «ΔΡΑΣΕΙΣ ΨΗΦΙΑΚΟΥ ΜΕΤΑΣΧΗΜΑΤΙΣΜΟΥ ΠΛΗΝ ΟΙΚΟΝΟΜΙΚΗΣ ΔΙΑΧΕΙΡΙΣΗΣ ΚΑΙ ΠΛΗΝ ΔΙΑΧΕΙΡΙΣΗΣ ΕΠΙΧΕΙΡΗΣΙΑΚΩΝ ΔΙΑΔΙΚΑΣΙΩΝ»",
          "cpvs": [
            {
              "key": "80533100-0",
              "value": "Υπηρεσίες εκπαίδευσης στον τομέα της πληροφορικής"
            },
            {
              "key": "48600000-4",
              "value": "Πακέτα λογισμικού βάσεων δεδομένων και λειτουργικών συστημάτων"
            },
            {
              "key": "72254100-1",
              "value": "Υπηρεσίες δοκιμής συστημάτων πληροφορικής"
            },
            {
              "key": "79131000-1",
              "value": "Υπηρεσίες τεκμηρίωσης"
            }
          ],
          "greenContracts": {
            "key": "1",
            "value": "Δεν εμπίπτει στο ΕΣΔ"
          },
          "goodServices": null,
          "budgetCode": null
        },
        {
          "quantity": 1,
          "type": {
            "key": "AG-001",
            "value": "Μελέτη"
          },
          "costWithoutVAT": 210247.26,
          "vat": "24",
          "currency": {
            "key": "EUR",
            "value": "Ευρώ"
          },
          "shortDescription": "Διακήρυξη διαγωνισμού που αφορά στο Υποέργο 2 της Πράξης «Ανάπτυξη Εφαρμογών Έξυπνων Πόλεων και Τεχνολογιών για το Διαδίκτυο των Αντικειμένων (ΙΟΤ) του Δήμου Ξάνθης » (ΜΙS 6003079) και συγχρηματοδοτείται από το Ευρωπαϊκό Ταμείο Περιφερειακής Ανάπτυξης για ΤΜΗΜΑ 2: «ΔΡΑΣΕΙΣ ΟΙΚΟΝΟΜΙΚΗΣ ΔΙΑΧΕΙΡΙΣΗΣ ΚΑΙ ΔΙΑΧΕΙΡΙΣΗΣ ΕΠΙΧΕΙΡΗΣΙΑΚΩΝ ΔΙΑΔΙΚΑΣΙΩΝ»",
          "cpvs": [
            {
              "key": "80533100-0",
              "value": "Υπηρεσίες εκπαίδευσης στον τομέα της πληροφορικής"
            },
            {
              "key": "79131000-1",
              "value": "Υπηρεσίες τεκμηρίωσης"
            },
            {
              "key": "72254100-1",
              "value": "Υπηρεσίες δοκιμής συστημάτων πληροφορικής"
            },
            {
              "key": "79999100-4",
              "value": "Υπηρεσίες σάρωσης"
            },
            {
              "key": "48600000-4",
              "value": "Πακέτα λογισμικού βάσεων δεδομένων και λειτουργικών συστημάτων"
            }
          ],
          "greenContracts": {
            "key": "1",
            "value": "Δεν εμπίπτει στο ΕΣΔ"
          },
          "goodServices": null,
          "budgetCode": null
        }
      ],
      "additionalContractTypes": [
        {
          "additionalContractType": {
            "key": "3",
            "value": "Υπηρεσίες"
          }
        }
      ],
      "mixedContract": true,
      "offersValidTime": 12,
      "offersValidTimeUnitOfMeasure": {
        "key": "3",
        "value": "Μήνες"
      },
      "maxNumberOfContractors": null,
      "optionRight": {
        "key": "2",
        "value": "Όχι"
      },
      "optionRightDescription": null,
      "abortReason": null,
      "auctionRefNo": [],
      "amendsNoticeRefNo": [],
      "cpv_codes_extracted": [
        "80533100",
        "48600000",
        "72254100",
        "79131000",
        "79999100"
      ],
      "cpv_divisions": [
        "80",
        "48",
        "72",
        "79"
      ],
      "all_domains": [
        "Education & Training",
        "Software & Information Systems",
        "IT Services",
        "Business Services (Legal/Marketing/Recruitment/Security/Print)"
      ],
      "primary_domain": "Software & Information Systems"
    },
    {
      "title": "Προκήρυξη Ε.Ε. - Δράσεις Ψηφιακού Μετασχηματισμού Δήμου Ξάνθης",
      "referenceNumber": "26PROC018453822",
      "signedDate": "2026-02-04T00:00:00",
      "publishedDate": "2026-02-06T00:00:00",
      "finalSubmissionDate": "2026-03-16T15:00:00",
      "submissionDate": "2026-02-10T08:31:25.09",
      "lastUpdateDate": null,
      "cancelled": false,
      "cancellationDate": null,
      "cancellationType": null,
      "cancellationReason": null,
      "cancellationADA": null,
      "amendPreviousNotice": false,
      "amendedNoticeADAM": null,
      "frameworkAgreementNoticeADAM": null,
      "protocolNumber": null,
      "authorEmail": null,
      "aaht": "1007.Ε80601.0001",
      "biddingWebsite": "https://nepps.eprocurement.gov.gr/",
      "organizationVatNumber": null,
      "greekOrganizationVatNumber": null,
      "budget": null,
      "commitmentNo": null,
      "relatedNoticeADAM": null,
      "numberOfSections": 2,
      "nutsCode": {
        "key": "EL512",
        "value": "Ξάνθη"
      },
      "nutsCity": "Ξάνθη",
      "nutsPostalCode": "67132",
      "nutsCountry": {
        "key": "GR",
        "value": "Ελλάδα"
      },
      "assignedContract": {
        "key": "2",
        "value": "Όχι"
      },
      "socialContract": {
        "key": "2",
        "value": "Όχι"
      },
      "centralGovernmentAuthority": {
        "key": "2",
        "value": "Όχι"
      },
      "contractingData": {
        "unitsOperator": {
          "key": "93861",
          "value": "ΔΙΕΥΘΥΝΣΗ ΟΙΚΟΝΟΜΙΚΩΝ ΥΠΗΡΕΣΙΩΝ"
        },
        "signers": {
          "key": "100048749",
          "value": "ΣΙΑΜΠΑΝ ΜΠΑΝΤΑΚ - Αντιδήμαρχος"
        }
      },
      "fundingDetails": {
        "publicFundingRef": "Ε2637",
        "publicFundingRefNum": "2025ΣΕ26370105",
        "publicFundingRefOps": "6003079",
        "cofundProgramRef": null,
        "selfFundProgramRef": null,
        "espaFundProgramRef": null,
        "regularBudgetFundedProgramRef": null
      },
      "systemicNumbers": [
        {
          "systemicNumber": "398101"
        },
        {
          "systemicNumber": "398081"
        }
      ],
      "approvedRequests": [
        {
          "code": "25REQ018241030"
        }
      ],
      "contractingAuthorities": [
        {
          "contractingAuthority": {
            "key": "9",
            "value": "ΝΠΔΔ"
          }
        }
      ],
      "nutsCodes": [
        {
          "nutsCode": {
            "key": "EL512",
            "value": "Ξάνθη"
          }
        }
      ],
      "organization": {
        "key": "6220",
        "value": "ΔΗΜΟΣ ΞΑΝΘΗΣ"
      },
      "typeOfProcedure": {
        "key": "1",
        "value": "Ανοιχτή διαδικασία"
      },
      "contractType": {
        "key": "13",
        "value": "Προμήθειες"
      },
      "awardProcedure": null,
      "centralizedMarkets": [
        {
          "centralizedMarket": {
            "key": "8",
            "value": "Δεν χρησιμοποιείται"
          }
        }
      ],
      "legalContext": {
        "key": "4",
        "value": "ν.4412/2016 - Βιβλίο Ι – άνω των ορίων"
      },
      "conductingProceedings": {
        "key": "1",
        "value": "Ηλεκτρονική Διαδικασία"
      },
      "digitalPlatform": {
        "key": "3",
        "value": "ΕΣΗΔΗΣ ΠΥ"
      },
      "criteriaCode": {
        "key": "1",
        "value": "Βάσει κόστους – βέλτιστη σχέση ποιότητας – τιμής"
      },
      "classificationOfPublicLawOrganization": {
        "key": "2",
        "value": "ΟΤΑ"
      },
      "noticeType": {
        "key": "2",
        "value": "Προκήρυξη"
      },
      "contractingAuthorityActivity": {
        "key": "1",
        "value": "Γενικές δημόσιες υπηρεσίες"
      },
      "contractDuration": 18,
      "contractDurationUnitOfMeasure": {
        "key": "3",
        "value": "Μήνες"
      },
      "totalCostWithVAT": 588721.35,
      "totalCostWithoutVAT": 474775.28,
      "objectDetails": [
        {
          "quantity": 1,
          "type": {
            "key": "AG-001",
            "value": "Μελέτη"
          },
          "costWithoutVAT": 210247.26,
          "vat": "24",
          "currency": {
            "key": "EUR",
            "value": "Ευρώ"
          },
          "shortDescription": "Προκήρυξη στην Ε.Ε. διαγωνισμού που αφορά στο Υποέργο 2 της Πράξης «Ανάπτυξη Εφαρμογών Έξυπνων Πόλεων και Τεχνολογιών για το Διαδίκτυο των Αντικειμένων (ΙΟΤ) του Δήμου Ξάνθης » (ΜΙS 6003079) και συγχρηματοδοτείται από το Ευρωπαϊκό Ταμείο Περιφερειακής Ανάπτυξης για ΤΜΗΜΑ 2: «ΔΡΑΣΕΙΣ ΟΙΚΟΝΟΜΙΚΗΣ ΔΙΑΧΕΙΡΙΣΗΣ ΚΑΙ ΔΙΑΧΕΙΡΙΣΗΣ ΕΠΙΧΕΙΡΗΣΙΑΚΩΝ ΔΙΑΔΙΚΑΣΙΩΝ»",
          "cpvs": [
            {
              "key": "79131000-1",
              "value": "Υπηρεσίες τεκμηρίωσης"
            },
            {
              "key": "72254100-1",
              "value": "Υπηρεσίες δοκιμής συστημάτων πληροφορικής"
            },
            {
              "key": "80533100-0",
              "value": "Υπηρεσίες εκπαίδευσης στον τομέα της πληροφορικής"
            },
            {
              "key": "48600000-4",
              "value": "Πακέτα λογισμικού βάσεων δεδομένων και λειτουργικών συστημάτων"
            },
            {
              "key": "79999100-4",
              "value": "Υπηρεσίες σάρωσης"
            }
          ],
          "greenContracts": {
            "key": "1",
            "value": "Δεν εμπίπτει στο ΕΣΔ"
          },
          "goodServices": null,
          "budgetCode": null
        },
        {
          "quantity": 1,
          "type": {
            "key": "AG-001",
            "value": "Μελέτη"
          },
          "costWithoutVAT": 264528.02,
          "vat": "24",
          "currency": {
            "key": "EUR",
            "value": "Ευρώ"
          },
          "shortDescription": "Προκήρυξη στην Ε.Ε. διαγωνισμού που αφορά στο Υποέργο 2 της Πράξης «Ανάπτυξη Εφαρμογών Έξυπνων Πόλεων και Τεχνολογιών για το Διαδίκτυο των Αντικειμένων (ΙΟΤ) του Δήμου Ξάνθης » (ΜΙS 6003079) και συγχρηματοδοτείται από το Ευρωπαϊκό Ταμείο Περιφερειακής Ανάπτυξης για ΤΜΗΜΑ 1: «ΔΡΑΣΕΙΣ ΨΗΦΙΑΚΟΥ ΜΕΤΑΣΧΗΜΑΤΙΣΜΟΥ ΠΛΗΝ ΟΙΚΟΝΟΜΙΚΗΣ ΔΙΑΧΕΙΡΙΣΗΣ ΚΑΙ ΠΛΗΝ ΔΙΑΧΕΙΡΙΣΗΣ ΕΠΙΧΕΙΡΗΣΙΑΚΩΝ ΔΙΑΔΙΚΑΣΙΩΝ»",
          "cpvs": [
            {
              "key": "79131000-1",
              "value": "Υπηρεσίες τεκμηρίωσης"
            },
            {
              "key": "48600000-4",
              "value": "Πακέτα λογισμικού βάσεων δεδομένων και λειτουργικών συστημάτων"
            },
            {
              "key": "80533100-0",
              "value": "Υπηρεσίες εκπαίδευσης στον τομέα της πληροφορικής"
            },
            {
              "key": "72254100-1",
              "value": "Υπηρεσίες δοκιμής συστημάτων πληροφορικής"
            }
          ],
          "greenContracts": {
            "key": "1",
            "value": "Δεν εμπίπτει στο ΕΣΔ"
          },
          "goodServices": null,
          "budgetCode": null
        }
      ],
      "additionalContractTypes": [
        {
          "additionalContractType": {
            "key": "3",
            "value": "Υπηρεσίες"
          }
        }
      ],
      "mixedContract": true,
      "offersValidTime": 12,
      "offersValidTimeUnitOfMeasure": {
        "key": "3",
        "value": "Μήνες"
      },
      "maxNumberOfContractors": null,
      "optionRight": {
        "key": "2",
        "value": "Όχι"
      },
      "optionRightDescription": null,
      "abortReason": null,
      "auctionRefNo": [],
      "amendsNoticeRefNo": [],
      "cpv_codes_extracted": [
        "79131000",
        "72254100",
        "80533100",
        "48600000",
        "79999100"
      ],
      "cpv_divisions": [
        "79",
        "72",
        "80",
        "48"
      ],
      "all_domains": [
        "Business Services (Legal/Marketing/Recruitment/Security/Print)",
        "IT Services",
        "Education & Training",
        "Software & Information Systems"
      ],
      "primary_domain": "Software & Information Systems"
    }
  ]
}