{
  "domain": "Agriculture & Forestry",
  "count": 3,
  "items": [
    {
      "title": "ΠΡΟΜΗΘΕΙΑ ΤΡΟΦΙΜΩΝ ΓΙΑ ΤΙΣ ΑΝΑΓΚΕΣ ΤΩΝ ΠΑΙΔΙΚΩΝ ΣΤΑΘΜΩΝ ΚΑΙ ΤΟΥ ΚΑΠΗ ΔΗΜΟΥ ΤΡΙΦΥΛΙΑΣ",
      "referenceNumber": "26SYMV018480451",
      "prevReferenceNo": null,
      "noticeReferenceNumber": null,
      "submissionDate": "2026-02-13T13:59:24.06",
      "lastUpdateDate": null,
      "contractSignedDate": "2026-02-13",
      "startDate": "2026-02-13",
      "noEndDate": true,
      "endDate": null,
      "cancelled": false,
      "cancellationDate": null,
      "cancellationType": null,
      "cancellationReason": null,
      "cancellationADA": null,
      "decisionRelatedAda": null,
      "contractNumber": "1811",
      "authorEmail": null,
      "organizationVatNumber": "800173110",
      "greekOrganizationVatNumber": true,
      "commitmentNo": null,
      "diavgeiaADA": null,
      "aaht": "1007.Ε84406.0001",
      "budget": null,
      "contractBudget": 147551.22,
      "bidsSubmitted": null,
      "maxBidsSubmitted": 1,
      "numberOfSections": 6,
      "assignedContract": {
        "key": "2",
        "value": "Όχι"
      },
      "socialContract": {
        "key": "1",
        "value": "Ναι"
      },
      "centralGovernmentAuthority": {
        "key": "2",
        "value": "Όχι"
      },
      "nutsCodes": [
        {
          "nutsCode": {
            "key": "EL653",
            "value": "Λακωνία, Μεσσηνία"
          }
        }
      ],
      "approvedRequestsList": [],
      "organization": {
        "key": "6300",
        "value": "ΔΗΜΟΣ ΤΡΙΦΥΛΙΑΣ"
      },
      "procedureType": {
        "key": "12",
        "value": "Διαπραγμάτευση χωρίς προηγούμενη δημοσίευση"
      },
      "awardProcedure": {
        "key": "60",
        "value": "Κατεπείγουσα ανάγκη οφειλόμενη σε  γεγονότα απρόβλεπτα για την αναθέτουσα αρχή"
      },
      "nutsCode": {
        "key": "EL653",
        "value": "Λακωνία, Μεσσηνία"
      },
      "nutsCity": "ΚΥΠΑΡΙΣΣΙΑ",
      "nutsPostalCode": "24500",
      "nutsCountry": {
        "key": "GR",
        "value": "Ελλάδα"
      },
      "centralizedMarkets": [
        {
          "centralizedMarket": {
            "key": "8",
            "value": "Δεν χρησιμοποιείται"
          }
        }
      ],
      "legalContext": {
        "key": "5",
        "value": "ν.4412/2016 - Βιβλίο Ι – κάτω των ορίων"
      },
      "contractType": {
        "key": "13",
        "value": "Προμήθειες"
      },
      "assignCriteria": {
        "key": "13",
        "value": "Βάσει τιμής"
      },
      "classificationOfPublicLawOrganization": {
        "key": "2",
        "value": "ΟΤΑ"
      },
      "typeOfContractingAuthority": {
        "key": "9",
        "value": "ΝΠΔΔ"
      },
      "contractingAuthorityActivity": {
        "key": "1",
        "value": "Γενικές δημόσιες υπηρεσίες"
      },
      "contractDuration": 18,
      "contractDurationUnitOfMeasure": {
        "key": "3",
        "value": "Μήνες"
      },
      "contractRelatedADA": {
        "number1": null,
        "number2": null,
        "number3": "9Α6ΣΩΗΕ-1Ε1"
      },
      "fundingDetails": {
        "publicFundingRef": null,
        "publicFundingRefNum": null,
        "publicFundingRefOps": null,
        "cofundProgramRef": null,
        "selfFundProgramRef": null,
        "espaFundProgramRef": null,
        "regularBudgetFundedProgramRef": "055.2260905001"
      },
      "contractingDataDetails": {
        "unitsOperator": {
          "key": "93264",
          "value": "ΑΥΤΟΤΕΛΕΣ ΓΡΑΦΕΙΟ ΠΡΟΓΡΑΜΜΑΤΙΣΜΟΥ, ΟΡΓΑΝΩΣΗΣ ΚΑΙ ΠΛΗΡΟΦΟΡΙΚΗΣ"
        },
        "signers": {
          "key": "100048757",
          "value": "ΓΕΩΡΓΙΟΣ ΛΕΒΕΝΤΑΚΗΣ - Δήμαρχος"
        },
        "contractingMembersDataList": [
          {
            "country": {
              "key": "GR",
              "value": "Ελλάδα"
            },
            "vatNumber": "800081227",
            "greekVatNumber": true,
            "name": "ΚΩΝ.ΚΑΤΡΙΤΣΗΣ & ΥΙΟΣ ΕΠΕ"
          }
        ]
      },
      "totalCostWithVAT": 166760.24,
      "totalCostWithoutVAT": 156312.98,
      "objectDetailsList": [
        {
          "quantity": 1,
          "type": {
            "key": "AG-001",
            "value": "Μελέτη"
          },
          "costWithoutVAT": 14232,
          "vat": "13",
          "currency": {
            "key": "EUR",
            "value": "Ευρώ"
          },
          "shortDescription": "ΕΙΔΗ ΑΡΤΟΠΟΙΕΙΟΥ",
          "cpvs": [
            {
              "key": "15612500-6",
              "value": "Προϊόντα αρτοποιίας"
            }
          ],
          "greenContracts": {
            "key": "1",
            "value": "Δεν εμπίπτει στο ΕΣΔ"
          },
          "goodServices": null,
          "cityOfConstruction": null,
          "countryOfDelivery": {
            "key": "GR",
            "value": "Ελλάδα"
          },
          "addressForDelivery": null,
          "postalCode": null,
          "city": "ΚΥΠΑΡΙΣΣΙΑ",
          "streetNumber": null,
          "budgetCode": null,
          "requestRefNo": "26AWRD018472800"
        },
        {
          "quantity": 1,
          "type": {
            "key": "AG-001",
            "value": "Μελέτη"
          },
          "costWithoutVAT": 33123,
          "vat": "13",
          "currency": {
            "key": "EUR",
            "value": "Ευρώ"
          },
          "shortDescription": "ΕΙΔΗ ΚΡΕΟΠΩΛΕΙΟΥ",
          "cpvs": [
            {
              "key": "15130000-8",
              "value": "Προϊόντα κρέατος"
            }
          ],
          "greenContracts": {
            "key": "1",
            "value": "Δεν εμπίπτει στο ΕΣΔ"
          },
          "goodServices": null,
          "cityOfConstruction": null,
          "countryOfDelivery": {
            "key": "GR",
            "value": "Ελλάδα"
          },
          "addressForDelivery": null,
          "postalCode": null,
          "city": "ΚΥΠΑΡΙΣΣΙΑ",
          "streetNumber": null,
          "budgetCode": null,
          "requestRefNo": "26AWRD018472800"
        },
        {
          "quantity": 1,
          "type": {
            "key": "AG-001",
            "value": "Μελέτη"
          },
          "costWithoutVAT": 17907.1,
          "vat": "13",
          "currency": {
            "key": "EUR",
            "value": "Ευρώ"
          },
          "shortDescription": "ΕΙΔΗ ΟΠΩΡΟΠΩΛΕΙΟΥ",
          "cpvs": [
            {
              "key": "15300000-1",
              "value": "Φρούτα"
            },
            {
              "key": "03220000-9",
              "value": "Λαχανικά"
            }
          ],
          "greenContracts": {
            "key": "1",
            "value": "Δεν εμπίπτει στο ΕΣΔ"
          },
          "goodServices": null,
          "cityOfConstruction": null,
          "countryOfDelivery": {
            "key": "GR",
            "value": "Ελλάδα"
          },
          "addressForDelivery": null,
          "postalCode": null,
          "city": "ΚΥΠΑΡΙΣΣΙΑ",
          "streetNumber": null,
          "budgetCode": null,
          "requestRefNo": "26AWRD018472800"
        },
        {
          "quantity": 1,
          "type": {
            "key": "AG-001",
            "value": "Μελέτη"
          },
          "costWithoutVAT": 75949.48,
          "vat": "0",
          "currency": {
            "key": "EUR",
            "value": "Ευρώ"
          },
          "shortDescription": "ΕΙΔΗ ΠΑΝΤΟΠΩΛΕΙΟΥ",
          "cpvs": [
            {
              "key": "15800000-6",
              "value": "Διάφορα προϊόντα διατροφής"
            }
          ],
          "greenContracts": {
            "key": "1",
            "value": "Δεν εμπίπτει στο ΕΣΔ"
          },
          "goodServices": null,
          "cityOfConstruction": null,
          "countryOfDelivery": {
            "key": "GR",
            "value": "Ελλάδα"
          },
          "addressForDelivery": null,
          "postalCode": null,
          "city": "ΚΥΠΑΡΙΣΣΙΑ",
          "streetNumber": null,
          "budgetCode": null,
          "requestRefNo": "26AWRD018472800"
        },
        {
          "quantity": 1,
          "type": {
            "key": "AG-001",
            "value": "Μελέτη"
          },
          "costWithoutVAT": 8367.4,
          "vat": "13",
          "currency": {
            "key": "EUR",
            "value": "Ευρώ"
          },
          "shortDescription": "ΚΑΤΕΨΥΓΜΕΝΑ ΕΙΔΗ",
          "cpvs": [
            {
              "key": "15331170-9",
              "value": "Κατεψυγμένα λαχανικά"
            },
            {
              "key": "15221000-3",
              "value": "Κατεψυγμένα ψάρια"
            }
          ],
          "greenContracts": {
            "key": "1",
            "value": "Δεν εμπίπτει στο ΕΣΔ"
          },
          "goodServices": null,
          "cityOfConstruction": null,
          "countryOfDelivery": {
            "key": "GR",
            "value": "Ελλάδα"
          },
          "addressForDelivery": null,
          "postalCode": null,
          "city": "ΚΥΠΑΡΙΣΣΙΑ",
          "streetNumber": null,
          "budgetCode": null,
          "requestRefNo": "26AWRD018472800"
        },
        {
          "quantity": 1,
          "type": {
            "key": "AG-001",
            "value": "Μελέτη"
          },
          "costWithoutVAT": 6734,
          "vat": "13",
          "currency": {
            "key": "EUR",
            "value": "Ευρώ"
          },
          "shortDescription": "ΕΛΑΙΟΛΑΔΟ",
          "cpvs": [
            {
              "key": "15411110-6",
              "value": "Ελαιόλαδο"
            }
          ],
          "greenContracts": {
            "key": "1",
            "value": "Δεν εμπίπτει στο ΕΣΔ"
          },
          "goodServices": null,
          "cityOfConstruction": null,
          "countryOfDelivery": {
            "key": "GR",
            "value": "Ελλάδα"
          },
          "addressForDelivery": null,
          "postalCode": null,
          "city": "ΚΥΠΑΡΙΣΣΙΑ",
          "streetNumber": null,
          "budgetCode": null,
          "requestRefNo": "26AWRD018472800"
        }
      ],
      "additionalContractTypes": null,
      "mixedContract": false,
      "requestRefNo": null,
      "nextRefNo": null,
      "nextExtended": null,
      "nextModified": null,
      "auctionRefNo": "26AWRD018472800",
      "paymentRefNo": [],
      "cpv_codes_extracted": [
        "15612500",
        "15130000",
        "15300000",
        "03220000",
        "15800000",
        "15331170",
        "15221000",
        "15411110"
      ],
      "cpv_divisions": [
        "15",
        "03"
      ],
      "all_domains": [
        "Food & Catering",
        "Agriculture & Forestry"
      ],
      "primary_domain": "Food & Catering"
    },
    {
      "title": "Προμήθεια Συσκευασμένων Σαλατών για Ανάγκες Μονάδων Α/Β Δεκέλειας και 2ου ΑΚΕ",
      "referenceNumber": "26SYMV018480397",
      "prevReferenceNo": null,
      "noticeReferenceNumber": null,
      "submissionDate": "2026-02-13T13:55:36.058",
      "lastUpdateDate": null,
      "contractSignedDate": "2026-02-13",
      "startDate": "2026-02-13",
      "noEndDate": false,
      "endDate": "2027-02-13",
      "cancelled": false,
      "cancellationDate": null,
      "cancellationType": null,
      "cancellationReason": null,
      "cancellationADA": null,
      "decisionRelatedAda": null,
      "contractNumber": "1/26",
      "authorEmail": null,
      "organizationVatNumber": "090153025",
      "greekOrganizationVatNumber": true,
      "commitmentNo": null,
      "diavgeiaADA": null,
      "aaht": "1011.2040000000.0014",
      "budget": null,
      "contractBudget": 18360,
      "bidsSubmitted": null,
      "maxBidsSubmitted": 2,
      "numberOfSections": 5,
      "assignedContract": {
        "key": "1",
        "value": "Ναι"
      },
      "socialContract": {
        "key": "2",
        "value": "Όχι"
      },
      "centralGovernmentAuthority": {
        "key": "1",
        "value": "Ναι"
      },
      "nutsCodes": [
        {
          "nutsCode": {
            "key": "EL3",
            "value": "ATTIKΗ"
          }
        }
      ],
      "approvedRequestsList": [],
      "organization": {
        "key": "6",
        "value": "ΥΠΟΥΡΓΕΙΟ ΕΘΝΙΚΗΣ ΑΜΥΝΑΣ"
      },
      "procedureType": {
        "key": "6",
        "value": "Απευθείας ανάθεση"
      },
      "awardProcedure": null,
      "nutsCode": {
        "key": "EL30",
        "value": "Aττική"
      },
      "nutsCity": "ΑΘΗΝΑ",
      "nutsPostalCode": "13671",
      "nutsCountry": {
        "key": "GR",
        "value": "Ελλάδα"
      },
      "centralizedMarkets": [
        {
          "centralizedMarket": {
            "key": "8",
            "value": "Δεν χρησιμοποιείται"
          }
        }
      ],
      "legalContext": {
        "key": "5",
        "value": "ν.4412/2016 - Βιβλίο Ι – κάτω των ορίων"
      },
      "contractType": {
        "key": "13",
        "value": "Προμήθειες"
      },
      "assignCriteria": {
        "key": "13",
        "value": "Βάσει τιμής"
      },
      "classificationOfPublicLawOrganization": {
        "key": "1",
        "value": "Κεντρική Κυβέρνηση"
      },
      "typeOfContractingAuthority": {
        "key": "12",
        "value": "Κεντρική Διοίκηση"
      },
      "contractingAuthorityActivity": {
        "key": "2",
        "value": "Άμυνα"
      },
      "contractDuration": 12,
      "contractDurationUnitOfMeasure": {
        "key": "3",
        "value": "Μήνες"
      },
      "contractRelatedADA": {
        "number1": null,
        "number2": null,
        "number3": "9ΝΓΣ6-Ζ15"
      },
      "fundingDetails": {
        "publicFundingRef": null,
        "publicFundingRefNum": null,
        "publicFundingRefOps": null,
        "cofundProgramRef": null,
        "selfFundProgramRef": "ΒΣΟ-ΒΣΜ-ΛΑΞ",
        "espaFundProgramRef": null,
        "regularBudgetFundedProgramRef": null
      },
      "contractingDataDetails": {
        "unitsOperator": {
          "key": "100101219",
          "value": "ΔΑΕ/ΔΟΥ Α/Β ΔΕΚΕΛΕΙΑΣ"
        },
        "signers": {
          "key": "100090645",
          "value": "ΜΑΡΓΑΡΙΤΗΣ ΜΟΥΜΟΥΡΗΣ - Επιτελάρχης"
        },
        "contractingMembersDataList": [
          {
            "country": {
              "key": "GR",
              "value": "Ελλάδα"
            },
            "vatNumber": "099004349",
            "greekVatNumber": true,
            "name": "EUROCATERING AE ΕΜΠΟΡΙΑΣ ΕΙΣΑΓΩΓΩΝ ΕΞΑΓΩΓΩΝ ΔΙΑΚΙΝΗΣΗΣ ΜΕΤΑΠΟΙΗΣΗΣ ΚΑΙ ΤΥΠΟΠΟΙΗΣΗΣ ΑΓΡΟΤΙΚΩΝ ΠΡΟΙΟΝΤΩΝ"
          }
        ]
      },
      "totalCostWithVAT": 20746.8,
      "totalCostWithoutVAT": 18360.0,
      "objectDetailsList": [
        {
          "quantity": 11000,
          "type": {
            "key": "C62",
            "value": "Τεμάχιο"
          },
          "costWithoutVAT": 18360,
          "vat": "13",
          "currency": {
            "key": "EUR",
            "value": "Ευρώ"
          },
          "shortDescription": "Συσκευασμένες Σαλάτες",
          "cpvs": [
            {
              "key": "03221320-5",
              "value": "Πράσινες σαλάτες"
            }
          ],
          "greenContracts": {
            "key": "1",
            "value": "Δεν εμπίπτει στο ΕΣΔ"
          },
          "goodServices": null,
          "cityOfConstruction": null,
          "countryOfDelivery": {
            "key": "GR",
            "value": "Ελλάδα"
          },
          "addressForDelivery": null,
          "postalCode": null,
          "city": "ΔΕΚΕΛΕΙΑ",
          "streetNumber": null,
          "budgetCode": null,
          "requestRefNo": "26AWRD018395549"
        }
      ],
      "additionalContractTypes": null,
      "mixedContract": false,
      "requestRefNo": null,
      "nextRefNo": null,
      "nextExtended": null,
      "nextModified": null,
      "auctionRefNo": "26AWRD018395549",
      "paymentRefNo": [],
      "cpv_codes_extracted": [
        "03221320"
      ],
      "cpv_divisions": [
        "03"
      ],
      "all_domains": [
        "Agriculture & Forestry"
      ],
      "primary_domain": "Agriculture & Forestry"
    },
    {
      "title": "Προμήθεια ειδών ιχθυοπωλείου (φρέσκα ψάρια)",
      "referenceNumber": "26SYMV018480197",
      "prevReferenceNo": null,
      "noticeReferenceNumber": null,
      "submissionDate": "2026-02-13T13:43:03.95",
      "lastUpdateDate": null,
      "contractSignedDate": "2026-02-13",
      "startDate": "2026-02-13",
      "noEndDate": false,
      "endDate": "2026-12-31",
      "cancelled": false,
      "cancellationDate": null,
      "cancellationType": null,
      "cancellationReason": null,
      "cancellationADA": null,
      "decisionRelatedAda": null,
      "contractNumber": "1211",
      "authorEmail": null,
      "organizationVatNumber": "090212982",
      "greekOrganizationVatNumber": false,
      "commitmentNo": null,
      "diavgeiaADA": null,
      "aaht": "1007.E80203.0001",
      "budget": null,
      "contractBudget": 24306,
      "bidsSubmitted": null,
      "maxBidsSubmitted": 1,
      "numberOfSections": 1,
      "assignedContract": {
        "key": "2",
        "value": "Όχι"
      },
      "socialContract": {
        "key": "2",
        "value": "Όχι"
      },
      "centralGovernmentAuthority": {
        "key": "2",
        "value": "Όχι"
      },
      "nutsCodes": [
        {
          "nutsCode": {
            "key": "EL514",
            "value": "Δράμα"
          }
        }
      ],
      "approvedRequestsList": [],
      "organization": {
        "key": "6143",
        "value": "ΔΗΜΟΣ ΚΑΤΩ ΝΕΥΡΟΚΟΠΙΟΥ"
      },
      "procedureType": {
        "key": "1",
        "value": "Ανοιχτή διαδικασία"
      },
      "awardProcedure": null,
      "nutsCode": {
        "key": "EL514",
        "value": "Δράμα"
      },
      "nutsCity": "Κ. ΝΕΥΡΟΚΟΠΙ",
      "nutsPostalCode": "66033",
      "nutsCountry": {
        "key": "GR",
        "value": "Ελλάδα"
      },
      "centralizedMarkets": [
        {
          "centralizedMarket": {
            "key": "8",
            "value": "Δεν χρησιμοποιείται"
          }
        }
      ],
      "legalContext": {
        "key": "4",
        "value": "ν.4412/2016 - Βιβλίο Ι – άνω των ορίων"
      },
      "contractType": {
        "key": "13",
        "value": "Προμήθειες"
      },
      "assignCriteria": {
        "key": "13",
        "value": "Βάσει τιμής"
      },
      "classificationOfPublicLawOrganization": {
        "key": "2",
        "value": "ΟΤΑ"
      },
      "typeOfContractingAuthority": {
        "key": "9",
        "value": "ΝΠΔΔ"
      },
      "contractingAuthorityActivity": {
        "key": "8",
        "value": "Κοινωνική προστασία"
      },
      "contractDuration": 11,
      "contractDurationUnitOfMeasure": {
        "key": "3",
        "value": "Μήνες"
      },
      "contractRelatedADA": {
        "number1": null,
        "number2": null,
        "number3": "9ΘΘΩΩΕ3-ΩΞΓ"
      },
      "fundingDetails": {
        "publicFundingRef": null,
        "publicFundingRefNum": null,
        "publicFundingRefOps": null,
        "cofundProgramRef": null,
        "selfFundProgramRef": null,
        "espaFundProgramRef": null,
        "regularBudgetFundedProgramRef": "0611"
      },
      "contractingDataDetails": {
        "unitsOperator": {
          "key": "100020160",
          "value": "ΤΜΗΜΑ ΠΡΟΥΠΟΛΟΓΙΣΜΟΥ ΛΟΓΙΣΤΗΡΙΟΥ ΟΙΚΟΝΟΜΙΚΗΣ ΠΛΗΡΟΦΟΡΗΣΗΣ"
        },
        "signers": {
          "key": "100084653",
          "value": "ΕΛΕΥΘΕΡΙΟΣ ΤΑΜΠΟΥΡΙΔΗΣ - Δήμαρχος"
        },
        "contractingMembersDataList": [
          {
            "country": {
              "key": "GR",
              "value": "Ελλάδα"
            },
            "vatNumber": "110477488",
            "greekVatNumber": false,
            "name": "ΤΣΑΜΠΑΖΗΣ ΣΤΑΥΡΟΣ "
          }
        ]
      },
      "totalCostWithVAT": 27465.78,
      "totalCostWithoutVAT": 24306.0,
      "objectDetailsList": [
        {
          "quantity": 2400,
          "type": {
            "key": "C62",
            "value": "Τεμάχιο"
          },
          "costWithoutVAT": 24306,
          "vat": "13",
          "currency": {
            "key": "EUR",
            "value": "Ευρώ"
          },
          "shortDescription": "Προμήθεια ειδών ιχθυοπωλείου (Φρέσκα Ψάρια) για τις ανάγκες του Δήμου Κ. Νευροκοπίου ",
          "cpvs": [
            {
              "key": "03310000-5",
              "value": "Ψάρια"
            }
          ],
          "greenContracts": {
            "key": "1",
            "value": "Δεν εμπίπτει στο ΕΣΔ"
          },
          "goodServices": null,
          "cityOfConstruction": null,
          "countryOfDelivery": {
            "key": "GR",
            "value": "Ελλάδα"
          },
          "addressForDelivery": null,
          "postalCode": null,
          "city": "Κ. Νευροκόπι",
          "streetNumber": null,
          "budgetCode": null,
          "requestRefNo": "26AWRD018480051"
        }
      ],
      "additionalContractTypes": null,
      "mixedContract": false,
      "requestRefNo": null,
      "nextRefNo": null,
      "nextExtended": null,
      "nextModified": null,
      "auctionRefNo": "26AWRD018480051",
      "paymentRefNo": [],
      "cpv_codes_extracted": [
        "03310000"
      ],
      "cpv_divisions": [
        "03"
      ],
      "all_domains": [
        "Agriculture & Forestry"
      ],
      "primary_domain": "Agriculture & Forestry"
    }
  ]
}